{
  "__data_type": "ITP ",
  "MAIN": {
    "type": "list",
    "value": [
      {
        "__struct_id": 0,
        "LIST": {
          "type": "list",
          "value": [
            {
              "__struct_id": 0,
              "ID": {
                "type": "byte",
                "value": 5
              },
              "LIST": {
                "type": "list",
                "value": [
                  {
                    "__struct_id": 0,
                    "RESREF": {
                      "type": "resref",
                      "value": "m2_cloth_003"
                    },
                    "STRREF": {
                      "type": "dword",
                      "value": 41242
                    }
                  },
                  {
                    "__struct_id": 0,
                    "RESREF": {
                      "type": "resref",
                      "value": "comcl001"
                    },
                    "STRREF": {
                      "type": "dword",
                      "value": 41002
                    }
                  },
                  {
                    "__struct_id": 0,
                    "RESREF": {
                      "type": "resref",
                      "value": "m2_cloth_010"
                    },
                    "STRREF": {
                      "type": "dword",
                      "value": 41247
                    }
                  },
                  {
                    "__struct_id": 0,
                    "RESREF": {
                      "type": "resref",
                      "value": "m2_cloth_006"
                    },
                    "STRREF": {
                      "type": "dword",
                      "value": 41244
                    }
                  },
                  {
                    "__struct_id": 0,
                    "RESREF": {
                      "type": "resref",
                      "value": "m2_cloth_009"
                    },
                    "STRREF": {
                      "type": "dword",
                      "value": 41244
                    }
                  },
                  {
                    "__struct_id": 0,
                    "RESREF": {
                      "type": "resref",
                      "value": "m2_cloth_005"
                    },
                    "STRREF": {
                      "type": "dword",
                      "value": 41243
                    }
                  },
                  {
                    "__struct_id": 0,
                    "RESREF": {
                      "type": "resref",
                      "value": "m2_cloth_007"
                    },
                    "STRREF": {
                      "type": "dword",
                      "value": 41245
                    }
                  },
                  {
                    "__struct_id": 0,
                    "RESREF": {
                      "type": "resref",
                      "value": "m2_cloth_012"
                    },
                    "STRREF": {
                      "type": "dword",
                      "value": 41245
                    }
                  },
                  {
                    "__struct_id": 0,
                    "RESREF": {
                      "type": "resref",
                      "value": "m2_cloth_013"
                    },
                    "STRREF": {
                      "type": "dword",
                      "value": 41245
                    }
                  },
                  {
                    "__struct_id": 0,
                    "RESREF": {
                      "type": "resref",
                      "value": "m2_cloth_002"
                    },
                    "STRREF": {
                      "type": "dword",
                      "value": 41241
                    }
                  },
                  {
                    "__struct_id": 0,
                    "RESREF": {
                      "type": "resref",
                      "value": "m2_cloth_011"
                    },
                    "STRREF": {
                      "type": "dword",
                      "value": 41241
                    }
                  },
                  {
                    "__struct_id": 0,
                    "RESREF": {
                      "type": "resref",
                      "value": "m2_cloth_004"
                    },
                    "STRREF": {
                      "type": "dword",
                      "value": 12904
                    }
                  },
                  {
                    "__struct_id": 0,
                    "RESREF": {
                      "type": "resref",
                      "value": "nw_cloth100"
                    },
                    "STRREF": {
                      "type": "dword",
                      "value": 12904
                    }
                  },
                  {
                    "__struct_id": 0,
                    "RESREF": {
                      "type": "resref",
                      "value": "m2_cloth_001"
                    },
                    "STRREF": {
                      "type": "dword",
                      "value": 41240
                    }
                  },
                  {
                    "__struct_id": 0,
                    "RESREF": {
                      "type": "resref",
                      "value": "m2_cloth_015"
                    },
                    "STRREF": {
                      "type": "dword",
                      "value": 59543
                    }
                  },
                  {
                    "__struct_id": 0,
                    "RESREF": {
                      "type": "resref",
                      "value": "m2_cloth_008"
                    },
                    "STRREF": {
                      "type": "dword",
                      "value": 41246
                    }
                  },
                  {
                    "__struct_id": 0,
                    "RESREF": {
                      "type": "resref",
                      "value": "m2_cloth_014"
                    },
                    "STRREF": {
                      "type": "dword",
                      "value": 41248
                    }
                  }
                ]
              },
              "STRREF": {
                "type": "dword",
                "value": 186
              }
            },
            {
              "__struct_id": 0,
              "ID": {
                "type": "byte",
                "value": 8
              },
              "LIST": {
                "type": "list",
                "value": [
                  {
                    "__struct_id": 0,
                    "RESREF": {
                      "type": "resref",
                      "value": "m2_armor_002"
                    },
                    "STRREF": {
                      "type": "dword",
                      "value": 41238
                    }
                  },
                  {
                    "__struct_id": 0,
                    "RESREF": {
                      "type": "resref",
                      "value": "m2_armor_003"
                    },
                    "STRREF": {
                      "type": "dword",
                      "value": 41238
                    }
                  }
                ]
              },
              "STRREF": {
                "type": "dword",
                "value": 4818
              }
            },
            {
              "__struct_id": 0,
              "ID": {
                "type": "byte",
                "value": 9
              },
              "STRREF": {
                "type": "dword",
                "value": 6739
              }
            },
            {
              "__struct_id": 0,
              "ID": {
                "type": "byte",
                "value": 6
              },
              "STRREF": {
                "type": "dword",
                "value": 4815
              }
            },
            {
              "__struct_id": 0,
              "ID": {
                "type": "byte",
                "value": 7
              },
              "LIST": {
                "type": "list",
                "value": [
                  {
                    "__struct_id": 0,
                    "RESREF": {
                      "type": "resref",
                      "value": "m2_armor_001"
                    },
                    "STRREF": {
                      "type": "dword",
                      "value": 41237
                    }
                  },
                  {
                    "__struct_id": 0,
                    "RESREF": {
                      "type": "resref",
                      "value": "m2_armor_004"
                    },
                    "STRREF": {
                      "type": "dword",
                      "value": 41239
                    }
                  }
                ]
              },
              "STRREF": {
                "type": "dword",
                "value": 6669
              }
            },
            {
              "__struct_id": 0,
              "ID": {
                "type": "byte",
                "value": 58
              },
              "STRREF": {
                "type": "dword",
                "value": 6813
              }
            },
            {
              "__struct_id": 0,
              "LIST": {
                "type": "list",
                "value": [
                  {
                    "__struct_id": 0,
                    "ID": {
                      "type": "byte",
                      "value": 11
                    },
                    "STRREF": {
                      "type": "dword",
                      "value": 6822
                    }
                  },
                  {
                    "__struct_id": 0,
                    "ID": {
                      "type": "byte",
                      "value": 10
                    },
                    "STRREF": {
                      "type": "dword",
                      "value": 6741
                    }
                  },
                  {
                    "__struct_id": 0,
                    "ID": {
                      "type": "byte",
                      "value": 12
                    },
                    "STRREF": {
                      "type": "dword",
                      "value": 6742
                    }
                  }
                ]
              },
              "STRREF": {
                "type": "dword",
                "value": 6740
              }
            }
          ]
        },
        "STRREF": {
          "type": "dword",
          "value": 335
        }
      },
      {
        "__struct_id": 0,
        "LIST": {
          "type": "list",
          "value": [
            {
              "__struct_id": 0,
              "ID": {
                "type": "byte",
                "value": 55
              },
              "STRREF": {
                "type": "dword",
                "value": 6810
              }
            },
            {
              "__struct_id": 0,
              "ID": {
                "type": "byte",
                "value": 13
              },
              "STRREF": {
                "type": "dword",
                "value": 6744
              }
            },
            {
              "__struct_id": 0,
              "ID": {
                "type": "byte",
                "value": 63
              },
              "STRREF": {
                "type": "dword",
                "value": 6831
              }
            },
            {
              "__struct_id": 0,
              "ID": {
                "type": "byte",
                "value": 59
              },
              "STRREF": {
                "type": "dword",
                "value": 6814
              }
            },
            {
              "__struct_id": 0,
              "ID": {
                "type": "byte",
                "value": 14
              },
              "LIST": {
                "type": "list",
                "value": [
                  {
                    "__struct_id": 0,
                    "RESREF": {
                      "type": "resref",
                      "value": "m2seal_golem"
                    },
                    "STRREF": {
                      "type": "dword",
                      "value": 65221
                    }
                  },
                  {
                    "__struct_id": 0,
                    "RESREF": {
                      "type": "resref",
                      "value": "m2q3e_wolfpelt"
                    },
                    "STRREF": {
                      "type": "dword",
                      "value": 41172
                    }
                  }
                ]
              },
              "STRREF": {
                "type": "dword",
                "value": 6809
              }
            },
            {
              "__struct_id": 0,
              "ID": {
                "type": "byte",
                "value": 56
              },
              "STRREF": {
                "type": "dword",
                "value": 6811
              }
            }
          ]
        },
        "STRREF": {
          "type": "dword",
          "value": 6743
        }
      },
      {
        "__struct_id": 0,
        "LIST": {
          "type": "list",
          "value": [
            {
              "__struct_id": 0,
              "ID": {
                "type": "byte",
                "value": 60
              },
              "LIST": {
                "type": "list",
                "value": [
                  {
                    "__struct_id": 0,
                    "RESREF": {
                      "type": "resref",
                      "value": "m2q3g_cultjourn"
                    },
                    "STRREF": {
                      "type": "dword",
                      "value": 41174
                    }
                  },
                  {
                    "__struct_id": 0,
                    "RESREF": {
                      "type": "resref",
                      "value": "m2q01idyddjour"
                    },
                    "STRREF": {
                      "type": "dword",
                      "value": 41009
                    }
                  },
                  {
                    "__struct_id": 0,
                    "RESREF": {
                      "type": "resref",
                      "value": "m2q3kexpjourn"
                    },
                    "STRREF": {
                      "type": "dword",
                      "value": 65217
                    }
                  },
                  {
                    "__struct_id": 0,
                    "RESREF": {
                      "type": "resref",
                      "value": "m2q5cultjrnl"
                    },
                    "STRREF": {
                      "type": "dword",
                      "value": 41218
                    }
                  },
                  {
                    "__struct_id": 0,
                    "RESREF": {
                      "type": "resref",
                      "value": "m2q01timaskdeath"
                    },
                    "STRREF": {
                      "type": "dword",
                      "value": 41015
                    }
                  },
                  {
                    "__struct_id": 0,
                    "RESREF": {
                      "type": "resref",
                      "value": "m2q01timaskfire"
                    },
                    "STRREF": {
                      "type": "dword",
                      "value": 41017
                    }
                  },
                  {
                    "__struct_id": 0,
                    "RESREF": {
                      "type": "resref",
                      "value": "m2q01timaskice"
                    },
                    "STRREF": {
                      "type": "dword",
                      "value": 41019
                    }
                  },
                  {
                    "__struct_id": 0,
                    "RESREF": {
                      "type": "resref",
                      "value": "m2q01timasklife"
                    },
                    "STRREF": {
                      "type": "dword",
                      "value": 41021
                    }
                  },
                  {
                    "__struct_id": 0,
                    "RESREF": {
                      "type": "resref",
                      "value": "m2q01timaskreson"
                    },
                    "STRREF": {
                      "type": "dword",
                      "value": 41023
                    }
                  },
                  {
                    "__struct_id": 0,
                    "RESREF": {
                      "type": "resref",
                      "value": "m2q5xkarfrag"
                    },
                    "STRREF": {
                      "type": "dword",
                      "value": 41233
                    }
                  },
                  {
                    "__struct_id": 0,
                    "RESREF": {
                      "type": "resref",
                      "value": "m2q2gjrnrelmar"
                    },
                    "STRREF": {
                      "type": "dword",
                      "value": 41148
                    }
                  },
                  {
                    "__struct_id": 0,
                    "RESREF": {
                      "type": "resref",
                      "value": "m2q1itkarjourn"
                    },
                    "STRREF": {
                      "type": "dword",
                      "value": 41085
                    }
                  },
                  {
                    "__struct_id": 0,
                    "RESREF": {
                      "type": "resref",
                      "value": "m2q3itjournhero"
                    },
                    "STRREF": {
                      "type": "dword",
                      "value": 66853
                    }
                  },
                  {
                    "__struct_id": 0,
                    "RESREF": {
                      "type": "resref",
                      "value": "m2q2ittreatspiri"
                    },
                    "STRREF": {
                      "type": "dword",
                      "value": 41158
                    }
                  },
                  {
                    "__struct_id": 0,
                    "RESREF": {
                      "type": "resref",
                      "value": "m2q3iwanevbedjou"
                    },
                    "STRREF": {
                      "type": "dword",
                      "value": 41188
                    }
                  },
                  {
                    "__struct_id": 0,
                    "RESREF": {
                      "type": "resref",
                      "value": "m2q3iwanevcook"
                    },
                    "STRREF": {
                      "type": "dword",
                      "value": 41190
                    }
                  },
                  {
                    "__struct_id": 0,
                    "RESREF": {
                      "type": "resref",
                      "value": "m2q3iwanevlabjou"
                    },
                    "STRREF": {
                      "type": "dword",
                      "value": 41194
                    }
                  }
                ]
              },
              "STRREF": {
                "type": "dword",
                "value": 6815
              }
            },
            {
              "__struct_id": 0,
              "LIST": {
                "type": "list",
                "value": [
                  {
                    "__struct_id": 0,
                    "ID": {
                      "type": "byte",
                      "value": 16
                    },
                    "STRREF": {
                      "type": "dword",
                      "value": 6745
                    }
                  },
                  {
                    "__struct_id": 0,
                    "ID": {
                      "type": "byte",
                      "value": 15
                    },
                    "STRREF": {
                      "type": "dword",
                      "value": 1520
                    }
                  },
                  {
                    "__struct_id": 0,
                    "ID": {
                      "type": "byte",
                      "value": 17
                    },
                    "STRREF": {
                      "type": "dword",
                      "value": 6746
                    }
                  },
                  {
                    "__struct_id": 0,
                    "ID": {
                      "type": "byte",
                      "value": 18
                    },
                    "STRREF": {
                      "type": "dword",
                      "value": 6747
                    }
                  },
                  {
                    "__struct_id": 0,
                    "ID": {
                      "type": "byte",
                      "value": 19
                    },
                    "STRREF": {
                      "type": "dword",
                      "value": 1530
                    }
                  }
                ]
              },
              "STRREF": {
                "type": "dword",
                "value": 186
              }
            },
            {
              "__struct_id": 0,
              "ID": {
                "type": "byte",
                "value": 64
              },
              "STRREF": {
                "type": "dword",
                "value": 83602
              }
            },
            {
              "__struct_id": 0,
              "ID": {
                "type": "byte",
                "value": 57
              },
              "LIST": {
                "type": "list",
                "value": [
                  {
                    "__struct_id": 0,
                    "RESREF": {
                      "type": "resref",
                      "value": "m2q1itgemsetara"
                    },
                    "STRREF": {
                      "type": "dword",
                      "value": 41079
                    }
                  },
                  {
                    "__struct_id": 0,
                    "RESREF": {
                      "type": "resref",
                      "value": "m2q1itgemwanev"
                    },
                    "STRREF": {
                      "type": "dword",
                      "value": 41083
                    }
                  },
                  {
                    "__struct_id": 0,
                    "RESREF": {
                      "type": "resref",
                      "value": "m2q1itgemshart"
                    },
                    "STRREF": {
                      "type": "dword",
                      "value": 41081
                    }
                  }
                ]
              },
              "STRREF": {
                "type": "dword",
                "value": 6812
              }
            },
            {
              "__struct_id": 0,
              "LIST": {
                "type": "list",
                "value": [
                  {
                    "__struct_id": 0,
                    "ID": {
                      "type": "byte",
                      "value": 21
                    },
                    "STRREF": {
                      "type": "dword",
                      "value": 6750
                    }
                  },
                  {
                    "__struct_id": 0,
                    "ID": {
                      "type": "byte",
                      "value": 22
                    },
                    "LIST": {
                      "type": "list",
                      "value": [
                        {
                          "__struct_id": 0,
                          "RESREF": {
                            "type": "resref",
                            "value": "m2q1itring02"
                          },
                          "STRREF": {
                            "type": "dword",
                            "value": 41089
                          }
                        },
                        {
                          "__struct_id": 0,
                          "RESREF": {
                            "type": "resref",
                            "value": "m2q1itring03"
                          },
                          "STRREF": {
                            "type": "dword",
                            "value": 41091
                          }
                        },
                        {
                          "__struct_id": 0,
                          "RESREF": {
                            "type": "resref",
                            "value": "m2q2cc06_signet"
                          },
                          "STRREF": {
                            "type": "dword",
                            "value": 41116
                          }
                        },
                        {
                          "__struct_id": 0,
                          "RESREF": {
                            "type": "resref",
                            "value": "m2q2e_ring4"
                          },
                          "STRREF": {
                            "type": "dword",
                            "value": 41144
                          }
                        },
                        {
                          "__struct_id": 0,
                          "RESREF": {
                            "type": "resref",
                            "value": "m2q2e_ring1"
                          },
                          "STRREF": {
                            "type": "dword",
                            "value": 41138
                          }
                        },
                        {
                          "__struct_id": 0,
                          "RESREF": {
                            "type": "resref",
                            "value": "m2q2e_ring3"
                          },
                          "STRREF": {
                            "type": "dword",
                            "value": 41142
                          }
                        },
                        {
                          "__struct_id": 0,
                          "RESREF": {
                            "type": "resref",
                            "value": "m2q2e_ring2"
                          },
                          "STRREF": {
                            "type": "dword",
                            "value": 41140
                          }
                        },
                        {
                          "__struct_id": 0,
                          "RESREF": {
                            "type": "resref",
                            "value": "m2q06itwilring"
                          },
                          "STRREF": {
                            "type": "dword",
                            "value": 41075
                          }
                        },
                        {
                          "__struct_id": 0,
                          "RESREF": {
                            "type": "resref",
                            "value": "m2q1itring01"
                          },
                          "STRREF": {
                            "type": "dword",
                            "value": 41087
                          }
                        }
                      ]
                    },
                    "STRREF": {
                      "type": "dword",
                      "value": 6751
                    }
                  }
                ]
              },
              "STRREF": {
                "type": "dword",
                "value": 6749
              }
            },
            {
              "__struct_id": 0,
              "ID": {
                "type": "byte",
                "value": 20
              },
              "STRREF": {
                "type": "dword",
                "value": 6748
              }
            },
            {
              "__struct_id": 0,
              "ID": {
                "type": "byte",
                "value": 23
              },
              "LIST": {
                "type": "list",
                "value": [
                  {
                    "__struct_id": 0,
                    "RESREF": {
                      "type": "resref",
                      "value": "m2q2cd07_scroll"
                    },
                    "STRREF": {
                      "type": "dword",
                      "value": 41123
                    }
                  },
                  {
                    "__struct_id": 0,
                    "RESREF": {
                      "type": "resref",
                      "value": "m2q2ce_cscroll1"
                    },
                    "STRREF": {
                      "type": "dword",
                      "value": 41123
                    }
                  },
                  {
                    "__struct_id": 0,
                    "RESREF": {
                      "type": "resref",
                      "value": "m2q2i_deadan"
                    },
                    "STRREF": {
                      "type": "dword",
                      "value": 41160
                    }
                  },
                  {
                    "__struct_id": 0,
                    "RESREF": {
                      "type": "resref",
                      "value": "m2q2i_deadbody"
                    },
                    "STRREF": {
                      "type": "dword",
                      "value": 41162
                    }
                  },
                  {
                    "__struct_id": 0,
                    "RESREF": {
                      "type": "resref",
                      "value": "m2q2e_key"
                    },
                    "STRREF": {
                      "type": "dword",
                      "value": 41137
                    }
                  },
                  {
                    "__struct_id": 0,
                    "RESREF": {
                      "type": "resref",
                      "value": "m2130gp"
                    },
                    "STRREF": {
                      "type": "dword",
                      "value": 535
                    }
                  },
                  {
                    "__struct_id": 0,
                    "RESREF": {
                      "type": "resref",
                      "value": "m2500gp"
                    },
                    "STRREF": {
                      "type": "dword",
                      "value": 535
                    }
                  },
                  {
                    "__struct_id": 0,
                    "RESREF": {
                      "type": "resref",
                      "value": "m2q2ce_hscroll1"
                    },
                    "STRREF": {
                      "type": "dword",
                      "value": 41127
                    }
                  },
                  {
                    "__struct_id": 0,
                    "RESREF": {
                      "type": "resref",
                      "value": "m2q2ce_hscroll2"
                    },
                    "STRREF": {
                      "type": "dword",
                      "value": 41127
                    }
                  },
                  {
                    "__struct_id": 0,
                    "RESREF": {
                      "type": "resref",
                      "value": "m2q2itmirrorvan"
                    },
                    "STRREF": {
                      "type": "dword",
                      "value": 41153
                    }
                  },
                  {
                    "__struct_id": 0,
                    "RESREF": {
                      "type": "resref",
                      "value": "m2q2cc_key"
                    },
                    "STRREF": {
                      "type": "dword",
                      "value": 41121
                    }
                  },
                  {
                    "__struct_id": 0,
                    "RESREF": {
                      "type": "resref",
                      "value": "m2q2cd_key"
                    },
                    "STRREF": {
                      "type": "dword",
                      "value": 41121
                    }
                  },
                  {
                    "__struct_id": 0,
                    "RESREF": {
                      "type": "resref",
                      "value": "m2q2ce_key"
                    },
                    "STRREF": {
                      "type": "dword",
                      "value": 41133
                    }
                  },
                  {
                    "__struct_id": 0,
                    "RESREF": {
                      "type": "resref",
                      "value": "m2q2ce_tjrnl"
                    },
                    "STRREF": {
                      "type": "dword",
                      "value": 41134
                    }
                  },
                  {
                    "__struct_id": 0,
                    "RESREF": {
                      "type": "resref",
                      "value": "m2q1srlimaskdeth"
                    },
                    "STRREF": {
                      "type": "dword",
                      "value": 41095
                    }
                  },
                  {
                    "__struct_id": 0,
                    "RESREF": {
                      "type": "resref",
                      "value": "m2q1srlimaskfire"
                    },
                    "STRREF": {
                      "type": "dword",
                      "value": 41097
                    }
                  },
                  {
                    "__struct_id": 0,
                    "RESREF": {
                      "type": "resref",
                      "value": "m2q1srlimaskice"
                    },
                    "STRREF": {
                      "type": "dword",
                      "value": 41099
                    }
                  },
                  {
                    "__struct_id": 0,
                    "RESREF": {
                      "type": "resref",
                      "value": "m2q1srlimasklife"
                    },
                    "STRREF": {
                      "type": "dword",
                      "value": 41101
                    }
                  },
                  {
                    "__struct_id": 0,
                    "RESREF": {
                      "type": "resref",
                      "value": "m2q1srlimaskreso"
                    },
                    "STRREF": {
                      "type": "dword",
                      "value": 41103
                    }
                  },
                  {
                    "__struct_id": 0,
                    "RESREF": {
                      "type": "resref",
                      "value": "m2q2bb14_key"
                    },
                    "STRREF": {
                      "type": "dword",
                      "value": 41110
                    }
                  },
                  {
                    "__struct_id": 0,
                    "RESREF": {
                      "type": "resref",
                      "value": "m2q2itnotetroll"
                    },
                    "STRREF": {
                      "type": "dword",
                      "value": 41156
                    }
                  }
                ]
              },
              "STRREF": {
                "type": "dword",
                "value": 6699
              }
            },
            {
              "__struct_id": 0,
              "ID": {
                "type": "byte",
                "value": 24
              },
              "LIST": {
                "type": "list",
                "value": [
                  {
                    "__struct_id": 0,
                    "RESREF": {
                      "type": "resref",
                      "value": "m2q2f2_poison"
                    },
                    "STRREF": {
                      "type": "dword",
                      "value": 41147
                    }
                  },
                  {
                    "__struct_id": 0,
                    "RESREF": {
                      "type": "resref",
                      "value": "m2q2g_antidote"
                    },
                    "STRREF": {
                      "type": "dword",
                      "value": 41151
                    }
                  }
                ]
              },
              "STRREF": {
                "type": "dword",
                "value": 6753
              }
            },
            {
              "__struct_id": 0,
              "ID": {
                "type": "byte",
                "value": 26
              },
              "STRREF": {
                "type": "dword",
                "value": 6754
              }
            }
          ]
        },
        "STRREF": {
          "type": "dword",
          "value": 1592
        }
      },
      {
        "__struct_id": 0,
        "ID": {
          "type": "byte",
          "value": 54
        },
        "LIST": {
          "type": "list",
          "value": [
            {
              "__struct_id": 0,
              "RESREF": {
                "type": "resref",
                "value": "aarin_amulet"
              },
              "STRREF": {
                "type": "dword",
                "value": 40998
              }
            },
            {
              "__struct_id": 0,
              "RESREF": {
                "type": "resref",
                "value": "m2q1italhtooth"
              },
              "STRREF": {
                "type": "dword",
                "value": 41077
              }
            },
            {
              "__struct_id": 0,
              "RESREF": {
                "type": "resref",
                "value": "m2q3h_letterfire"
              },
              "STRREF": {
                "type": "dword",
                "value": 41178
              }
            },
            {
              "__struct_id": 0,
              "RESREF": {
                "type": "resref",
                "value": "m2q3h_letterghos"
              },
              "STRREF": {
                "type": "dword",
                "value": 41178
              }
            },
            {
              "__struct_id": 0,
              "RESREF": {
                "type": "resref",
                "value": "m2q3h_letterjust"
              },
              "STRREF": {
                "type": "dword",
                "value": 41178
              }
            },
            {
              "__struct_id": 0,
              "RESREF": {
                "type": "resref",
                "value": "aribeth_ring"
              },
              "STRREF": {
                "type": "dword",
                "value": 41000
              }
            },
            {
              "__struct_id": 0,
              "RESREF": {
                "type": "resref",
                "value": "m2q2jkey"
              },
              "STRREF": {
                "type": "dword",
                "value": 41167
              }
            },
            {
              "__struct_id": 0,
              "RESREF": {
                "type": "resref",
                "value": "m2q3h_judgekey"
              },
              "STRREF": {
                "type": "dword",
                "value": 41177
              }
            },
            {
              "__struct_id": 0,
              "RESREF": {
                "type": "resref",
                "value": "m2q3h_riddlekey"
              },
              "STRREF": {
                "type": "dword",
                "value": 41185
              }
            },
            {
              "__struct_id": 0,
              "RESREF": {
                "type": "resref",
                "value": "m2q3i_karlatkey"
              },
              "STRREF": {
                "type": "dword",
                "value": 41201
              }
            },
            {
              "__struct_id": 0,
              "RESREF": {
                "type": "resref",
                "value": "m2q3i_quintkey"
              },
              "STRREF": {
                "type": "dword",
                "value": 41203
              }
            },
            {
              "__struct_id": 0,
              "RESREF": {
                "type": "resref",
                "value": "m2q2_nymphdagger"
              },
              "STRREF": {
                "type": "dword",
                "value": 65214
              }
            },
            {
              "__struct_id": 0,
              "RESREF": {
                "type": "resref",
                "value": "m2q2ccrbook"
              },
              "STRREF": {
                "type": "dword",
                "value": 65215
              }
            },
            {
              "__struct_id": 0,
              "RESREF": {
                "type": "resref",
                "value": "m2q05icrysegg"
              },
              "STRREF": {
                "type": "dword",
                "value": 41033
              }
            },
            {
              "__struct_id": 0,
              "RESREF": {
                "type": "resref",
                "value": "m2q05icrysfrog"
              },
              "STRREF": {
                "type": "dword",
                "value": 41035
              }
            },
            {
              "__struct_id": 0,
              "RESREF": {
                "type": "resref",
                "value": "m2q05icrysinsect"
              },
              "STRREF": {
                "type": "dword",
                "value": 41037
              }
            },
            {
              "__struct_id": 0,
              "RESREF": {
                "type": "resref",
                "value": "m2q05icrysskull"
              },
              "STRREF": {
                "type": "dword",
                "value": 41039
              }
            },
            {
              "__struct_id": 0,
              "RESREF": {
                "type": "resref",
                "value": "m2q04idelilahear"
              },
              "STRREF": {
                "type": "dword",
                "value": 41029
              }
            },
            {
              "__struct_id": 0,
              "RESREF": {
                "type": "resref",
                "value": "m2q5dergiabhead"
              },
              "STRREF": {
                "type": "dword",
                "value": 41220
              }
            },
            {
              "__struct_id": 0,
              "RESREF": {
                "type": "resref",
                "value": "m2q06iaarinpass"
              },
              "STRREF": {
                "type": "dword",
                "value": 42591
              }
            },
            {
              "__struct_id": 0,
              "RESREF": {
                "type": "resref",
                "value": "m2q2cbookmorag"
              },
              "STRREF": {
                "type": "dword",
                "value": 41114
              }
            },
            {
              "__struct_id": 0,
              "RESREF": {
                "type": "resref",
                "value": "elynwyd_ring"
              },
              "STRREF": {
                "type": "dword",
                "value": 41003
              }
            },
            {
              "__struct_id": 0,
              "RESREF": {
                "type": "resref",
                "value": "gate key"
              },
              "STRREF": {
                "type": "dword",
                "value": 47107
              }
            },
            {
              "__struct_id": 0,
              "RESREF": {
                "type": "resref",
                "value": "m2q05idungeonkey"
              },
              "STRREF": {
                "type": "dword",
                "value": 41044
              }
            },
            {
              "__struct_id": 0,
              "RESREF": {
                "type": "resref",
                "value": "m2q05idoorpuzkey"
              },
              "STRREF": {
                "type": "dword",
                "value": 41042
              }
            },
            {
              "__struct_id": 0,
              "RESREF": {
                "type": "resref",
                "value": "m2q3igulgheart"
              },
              "STRREF": {
                "type": "dword",
                "value": 41186
              }
            },
            {
              "__struct_id": 0,
              "RESREF": {
                "type": "resref",
                "value": "m2q05ibugbhead"
              },
              "STRREF": {
                "type": "dword",
                "value": 41031
              }
            },
            {
              "__struct_id": 0,
              "RESREF": {
                "type": "resref",
                "value": "m2q05iorchead"
              },
              "STRREF": {
                "type": "dword",
                "value": 41049
              }
            },
            {
              "__struct_id": 0,
              "RESREF": {
                "type": "resref",
                "value": "head_m2q2alent"
              },
              "STRREF": {
                "type": "dword",
                "value": 41005
              }
            },
            {
              "__struct_id": 0,
              "RESREF": {
                "type": "resref",
                "value": "m2q6a0seal"
              },
              "STRREF": {
                "type": "dword",
                "value": 41235
              }
            },
            {
              "__struct_id": 0,
              "RESREF": {
                "type": "resref",
                "value": "2q6_impgore"
              },
              "STRREF": {
                "type": "dword",
                "value": 42562
              }
            },
            {
              "__struct_id": 0,
              "RESREF": {
                "type": "resref",
                "value": "m2q2cbktomb"
              },
              "STRREF": {
                "type": "dword",
                "value": 41112
              }
            },
            {
              "__struct_id": 0,
              "RESREF": {
                "type": "resref",
                "value": "m2q3h_letterridd"
              },
              "STRREF": {
                "type": "dword",
                "value": 41182
              }
            },
            {
              "__struct_id": 0,
              "RESREF": {
                "type": "resref",
                "value": "m2q06ilettneva"
              },
              "STRREF": {
                "type": "dword",
                "value": 41071
              }
            },
            {
              "__struct_id": 0,
              "RESREF": {
                "type": "resref",
                "value": "m2q3j_quintlett"
              },
              "STRREF": {
                "type": "dword",
                "value": 41206
              }
            },
            {
              "__struct_id": 0,
              "RESREF": {
                "type": "resref",
                "value": "m2q06ilettsolomo"
              },
              "STRREF": {
                "type": "dword",
                "value": 41073
              }
            },
            {
              "__struct_id": 0,
              "RESREF": {
                "type": "resref",
                "value": "m2q1vardlet"
              },
              "STRREF": {
                "type": "dword",
                "value": 41105
              }
            },
            {
              "__struct_id": 0,
              "RESREF": {
                "type": "resref",
                "value": "m2q05igravekey"
              },
              "STRREF": {
                "type": "dword",
                "value": 41046
              }
            },
            {
              "__struct_id": 0,
              "RESREF": {
                "type": "resref",
                "value": "m2q3kscroll"
              },
              "STRREF": {
                "type": "dword",
                "value": 65219
              }
            },
            {
              "__struct_id": 0,
              "RESREF": {
                "type": "resref",
                "value": "m2q3e_brooch"
              },
              "STRREF": {
                "type": "dword",
                "value": 41168
              }
            },
            {
              "__struct_id": 0,
              "RESREF": {
                "type": "resref",
                "value": "m2q01iyesgarkey"
              },
              "STRREF": {
                "type": "dword",
                "value": 41014
              }
            },
            {
              "__struct_id": 0,
              "RESREF": {
                "type": "resref",
                "value": "2q6_quasitgore"
              },
              "STRREF": {
                "type": "dword",
                "value": 42570
              }
            },
            {
              "__struct_id": 0,
              "RESREF": {
                "type": "resref",
                "value": "m2q2arring"
              },
              "STRREF": {
                "type": "dword",
                "value": 41107
              }
            },
            {
              "__struct_id": 0,
              "RESREF": {
                "type": "resref",
                "value": "m2q2j7key"
              },
              "STRREF": {
                "type": "dword",
                "value": 41165
              }
            },
            {
              "__struct_id": 0,
              "RESREF": {
                "type": "resref",
                "value": "m2q1silvercharm"
              },
              "STRREF": {
                "type": "dword",
                "value": 41093
              }
            },
            {
              "__struct_id": 0,
              "RESREF": {
                "type": "resref",
                "value": "m2q3e_wolfhead"
              },
              "STRREF": {
                "type": "dword",
                "value": 41170
              }
            },
            {
              "__struct_id": 0,
              "RESREF": {
                "type": "resref",
                "value": "m2q03istirgeear"
              },
              "STRREF": {
                "type": "dword",
                "value": 41027
              }
            },
            {
              "__struct_id": 0,
              "RESREF": {
                "type": "resref",
                "value": "m2q3i_journkarla"
              },
              "STRREF": {
                "type": "dword",
                "value": 41198
              }
            },
            {
              "__struct_id": 0,
              "RESREF": {
                "type": "resref",
                "value": "m2q3j_journquint"
              },
              "STRREF": {
                "type": "dword",
                "value": 41204
              }
            },
            {
              "__struct_id": 0,
              "RESREF": {
                "type": "resref",
                "value": "m2q3_oathbelial"
              },
              "STRREF": {
                "type": "dword",
                "value": 41208
              }
            },
            {
              "__struct_id": 0,
              "RESREF": {
                "type": "resref",
                "value": "m2q3_oathkarlat"
              },
              "STRREF": {
                "type": "dword",
                "value": 41210
              }
            },
            {
              "__struct_id": 0,
              "RESREF": {
                "type": "resref",
                "value": "m2q3_oathquint"
              },
              "STRREF": {
                "type": "dword",
                "value": 41212
              }
            },
            {
              "__struct_id": 0,
              "RESREF": {
                "type": "resref",
                "value": "m2q3_phylactery"
              },
              "STRREF": {
                "type": "dword",
                "value": 41214
              }
            },
            {
              "__struct_id": 0,
              "RESREF": {
                "type": "resref",
                "value": "m2q05itombkey"
              },
              "STRREF": {
                "type": "dword",
                "value": 41060
              }
            },
            {
              "__struct_id": 0,
              "RESREF": {
                "type": "resref",
                "value": "2q6b_securekey"
              },
              "STRREF": {
                "type": "dword",
                "value": 42557
              }
            },
            {
              "__struct_id": 0,
              "RESREF": {
                "type": "resref",
                "value": "m2q2itkeytroll"
              },
              "STRREF": {
                "type": "dword",
                "value": 41110
              }
            },
            {
              "__struct_id": 0,
              "RESREF": {
                "type": "resref",
                "value": "m2q3iwanevcotkey"
              },
              "STRREF": {
                "type": "dword",
                "value": 41193
              }
            },
            {
              "__struct_id": 0,
              "RESREF": {
                "type": "resref",
                "value": "m2q3iwanevsumkey"
              },
              "STRREF": {
                "type": "dword",
                "value": 41197
              }
            },
            {
              "__struct_id": 0,
              "RESREF": {
                "type": "resref",
                "value": "m2q01iwardwanev"
              },
              "STRREF": {
                "type": "dword",
                "value": 41011
              }
            },
            {
              "__struct_id": 0,
              "RESREF": {
                "type": "resref",
                "value": "m2q05ileahring"
              },
              "STRREF": {
                "type": "dword",
                "value": 41047
              }
            },
            {
              "__struct_id": 0,
              "RESREF": {
                "type": "resref",
                "value": "m2q02iwyvernear"
              },
              "STRREF": {
                "type": "dword",
                "value": 41025
              }
            },
            {
              "__struct_id": 0,
              "RESREF": {
                "type": "resref",
                "value": "m2q05iyesgarear"
              },
              "STRREF": {
                "type": "dword",
                "value": 41061
              }
            },
            {
              "__struct_id": 0,
              "RESREF": {
                "type": "resref",
                "value": "it_key001"
              },
              "STRREF": {
                "type": "dword",
                "value": 41008
              }
            },
            {
              "__struct_id": 0,
              "RESREF": {
                "type": "resref",
                "value": "m2q05izamithkey"
              },
              "STRREF": {
                "type": "dword",
                "value": 41064
              }
            },
            {
              "__struct_id": 0,
              "RESREF": {
                "type": "resref",
                "value": "m2q05izamithkey2"
              },
              "STRREF": {
                "type": "dword",
                "value": 41066
              }
            },
            {
              "__struct_id": 0,
              "RESREF": {
                "type": "resref",
                "value": "m2q05izorear"
              },
              "STRREF": {
                "type": "dword",
                "value": 41067
              }
            }
          ]
        },
        "STRREF": {
          "type": "dword",
          "value": 6808
        }
      },
      {
        "__struct_id": 0,
        "LIST": {
          "type": "list",
          "value": [
            {
              "__struct_id": 0,
              "ID": {
                "type": "byte",
                "value": 0
              },
              "STRREF": {
                "type": "dword",
                "value": 6688
              }
            },
            {
              "__struct_id": 0,
              "ID": {
                "type": "byte",
                "value": 1
              },
              "STRREF": {
                "type": "dword",
                "value": 6689
              }
            },
            {
              "__struct_id": 0,
              "ID": {
                "type": "byte",
                "value": 2
              },
              "STRREF": {
                "type": "dword",
                "value": 6690
              }
            },
            {
              "__struct_id": 0,
              "ID": {
                "type": "byte",
                "value": 3
              },
              "STRREF": {
                "type": "dword",
                "value": 6691
              }
            },
            {
              "__struct_id": 0,
              "ID": {
                "type": "byte",
                "value": 4
              },
              "STRREF": {
                "type": "dword",
                "value": 6692
              }
            }
          ]
        },
        "STRREF": {
          "type": "dword",
          "value": 6687
        }
      },
      {
        "__struct_id": 0,
        "ID": {
          "type": "byte",
          "value": 53
        },
        "STRREF": {
          "type": "dword",
          "value": 6732
        }
      },
      {
        "__struct_id": 0,
        "LIST": {
          "type": "list",
          "value": [
            {
              "__struct_id": 0,
              "LIST": {
                "type": "list",
                "value": [
                  {
                    "__struct_id": 0,
                    "ID": {
                      "type": "byte",
                      "value": 27
                    },
                    "STRREF": {
                      "type": "dword",
                      "value": 6757
                    }
                  },
                  {
                    "__struct_id": 0,
                    "ID": {
                      "type": "byte",
                      "value": 28
                    },
                    "STRREF": {
                      "type": "dword",
                      "value": 6758
                    }
                  },
                  {
                    "__struct_id": 0,
                    "ID": {
                      "type": "byte",
                      "value": 29
                    },
                    "STRREF": {
                      "type": "dword",
                      "value": 6759
                    }
                  }
                ]
              },
              "STRREF": {
                "type": "dword",
                "value": 6756
              }
            },
            {
              "__struct_id": 0,
              "LIST": {
                "type": "list",
                "value": [
                  {
                    "__struct_id": 0,
                    "ID": {
                      "type": "byte",
                      "value": 32
                    },
                    "STRREF": {
                      "type": "dword",
                      "value": 6762
                    }
                  },
                  {
                    "__struct_id": 0,
                    "ID": {
                      "type": "byte",
                      "value": 30
                    },
                    "STRREF": {
                      "type": "dword",
                      "value": 6760
                    }
                  },
                  {
                    "__struct_id": 0,
                    "ID": {
                      "type": "byte",
                      "value": 31
                    },
                    "STRREF": {
                      "type": "dword",
                      "value": 6761
                    }
                  }
                ]
              },
              "STRREF": {
                "type": "dword",
                "value": 490
              }
            },
            {
              "__struct_id": 0,
              "LIST": {
                "type": "list",
                "value": [
                  {
                    "__struct_id": 0,
                    "ID": {
                      "type": "byte",
                      "value": 33
                    },
                    "STRREF": {
                      "type": "dword",
                      "value": 6764
                    }
                  },
                  {
                    "__struct_id": 0,
                    "ID": {
                      "type": "byte",
                      "value": 34
                    },
                    "LIST": {
                      "type": "list",
                      "value": [
                        {
                          "__struct_id": 0,
                          "RESREF": {
                            "type": "resref",
                            "value": "m2q1delilahdagr"
                          },
                          "STRREF": {
                            "type": "dword",
                            "value": 191
                          }
                        }
                      ]
                    },
                    "STRREF": {
                      "type": "dword",
                      "value": 6765
                    }
                  },
                  {
                    "__struct_id": 0,
                    "ID": {
                      "type": "byte",
                      "value": 35
                    },
                    "STRREF": {
                      "type": "dword",
                      "value": 6766
                    }
                  },
                  {
                    "__struct_id": 0,
                    "ID": {
                      "type": "byte",
                      "value": 36
                    },
                    "STRREF": {
                      "type": "dword",
                      "value": 6767
                    }
                  },
                  {
                    "__struct_id": 0,
                    "ID": {
                      "type": "byte",
                      "value": 37
                    },
                    "LIST": {
                      "type": "list",
                      "value": [
                        {
                          "__struct_id": 0,
                          "RESREF": {
                            "type": "resref",
                            "value": "2q6g_discipline"
                          },
                          "STRREF": {
                            "type": "dword",
                            "value": 42559
                          }
                        }
                      ]
                    },
                    "STRREF": {
                      "type": "dword",
                      "value": 6699
                    }
                  },
                  {
                    "__struct_id": 0,
                    "ID": {
                      "type": "byte",
                      "value": 38
                    },
                    "STRREF": {
                      "type": "dword",
                      "value": 6768
                    }
                  }
                ]
              },
              "STRREF": {
                "type": "dword",
                "value": 6763
              }
            },
            {
              "__struct_id": 0,
              "LIST": {
                "type": "list",
                "value": [
                  {
                    "__struct_id": 0,
                    "ID": {
                      "type": "byte",
                      "value": 39
                    },
                    "STRREF": {
                      "type": "dword",
                      "value": 6769
                    }
                  },
                  {
                    "__struct_id": 0,
                    "ID": {
                      "type": "byte",
                      "value": 40
                    },
                    "STRREF": {
                      "type": "dword",
                      "value": 6770
                    }
                  },
                  {
                    "__struct_id": 0,
                    "ID": {
                      "type": "byte",
                      "value": 41
                    },
                    "STRREF": {
                      "type": "dword",
                      "value": 6771
                    }
                  },
                  {
                    "__struct_id": 0,
                    "ID": {
                      "type": "byte",
                      "value": 42
                    },
                    "STRREF": {
                      "type": "dword",
                      "value": 6772
                    }
                  },
                  {
                    "__struct_id": 0,
                    "ID": {
                      "type": "byte",
                      "value": 61
                    },
                    "STRREF": {
                      "type": "dword",
                      "value": 6817
                    }
                  }
                ]
              },
              "STRREF": {
                "type": "dword",
                "value": 491
              }
            },
            {
              "__struct_id": 0,
              "ID": {
                "type": "byte",
                "value": 46
              },
              "STRREF": {
                "type": "dword",
                "value": 6775
              }
            },
            {
              "__struct_id": 0,
              "ID": {
                "type": "byte",
                "value": 47
              },
              "LIST": {
                "type": "list",
                "value": [
                  {
                    "__struct_id": 0,
                    "RESREF": {
                      "type": "resref",
                      "value": "weird gauntlet"
                    },
                    "STRREF": {
                      "type": "dword",
                      "value": 59544
                    }
                  }
                ]
              },
              "STRREF": {
                "type": "dword",
                "value": 6776
              }
            },
            {
              "__struct_id": 0,
              "LIST": {
                "type": "list",
                "value": [
                  {
                    "__struct_id": 0,
                    "ID": {
                      "type": "byte",
                      "value": 48
                    },
                    "STRREF": {
                      "type": "dword",
                      "value": 6778
                    }
                  },
                  {
                    "__struct_id": 0,
                    "ID": {
                      "type": "byte",
                      "value": 49
                    },
                    "STRREF": {
                      "type": "dword",
                      "value": 6779
                    }
                  },
                  {
                    "__struct_id": 0,
                    "ID": {
                      "type": "byte",
                      "value": 50
                    },
                    "LIST": {
                      "type": "list",
                      "value": [
                        {
                          "__struct_id": 0,
                          "RESREF": {
                            "type": "resref",
                            "value": "m2q3_karburn"
                          },
                          "STRREF": {
                            "type": "dword",
                            "value": 68131
                          }
                        },
                        {
                          "__struct_id": 0,
                          "RESREF": {
                            "type": "resref",
                            "value": "m2q3_karwand"
                          },
                          "STRREF": {
                            "type": "dword",
                            "value": 68133
                          }
                        }
                      ]
                    },
                    "STRREF": {
                      "type": "dword",
                      "value": 6780
                    }
                  }
                ]
              },
              "STRREF": {
                "type": "dword",
                "value": 6777
              }
            },
            {
              "__struct_id": 0,
              "ID": {
                "type": "byte",
                "value": 51
              },
              "STRREF": {
                "type": "dword",
                "value": 489
              }
            },
            {
              "__struct_id": 0,
              "LIST": {
                "type": "list",
                "value": [
                  {
                    "__struct_id": 0,
                    "ID": {
                      "type": "byte",
                      "value": 43
                    },
                    "STRREF": {
                      "type": "dword",
                      "value": 6774
                    }
                  },
                  {
                    "__struct_id": 0,
                    "ID": {
                      "type": "byte",
                      "value": 44
                    },
                    "STRREF": {
                      "type": "dword",
                      "value": 6819
                    }
                  },
                  {
                    "__struct_id": 0,
                    "ID": {
                      "type": "byte",
                      "value": 45
                    },
                    "STRREF": {
                      "type": "dword",
                      "value": 6820
                    }
                  },
                  {
                    "__struct_id": 0,
                    "ID": {
                      "type": "byte",
                      "value": 62
                    },
                    "STRREF": {
                      "type": "dword",
                      "value": 6821
                    }
                  }
                ]
              },
              "STRREF": {
                "type": "dword",
                "value": 6818
              }
            },
            {
              "__struct_id": 0,
              "ID": {
                "type": "byte",
                "value": 52
              },
              "STRREF": {
                "type": "dword",
                "value": 494
              }
            }
          ]
        },
        "STRREF": {
          "type": "dword",
          "value": 500
        }
      }
    ]
  }
}
