{
  "__data_type": "UTI ",
  "AddCost": {
    "type": "dword",
    "value": 0
  },
  "BaseItem": {
    "type": "int",
    "value": 52
  },
  "Charges": {
    "type": "byte",
    "value": 0
  },
  "Comment": {
    "type": "cexostring",
    "value": "protects Morag against Flame attacks\r\nM4Q1D2"
  },
  "Cost": {
    "type": "dword",
    "value": 165313
  },
  "Cursed": {
    "type": "byte",
    "value": 0
  },
  "DescIdentified": {
    "type": "cexolocstring",
    "value": {}
  },
  "Description": {
    "type": "cexolocstring",
    "value": {}
  },
  "Identified": {
    "type": "byte",
    "value": 0
  },
  "LocalizedName": {
    "type": "cexolocstring",
    "value": {
      "id": 49135
    }
  },
  "ModelPart1": {
    "type": "byte",
    "value": 1
  },
  "PaletteID": {
    "type": "byte",
    "value": 54
  },
  "Plot": {
    "type": "byte",
    "value": 1
  },
  "PropertiesList": {
    "type": "list",
    "value": [
      {
        "__struct_id": 0,
        "ChanceAppear": {
          "type": "byte",
          "value": 100
        },
        "CostTable": {
          "type": "byte",
          "value": 5
        },
        "CostValue": {
          "type": "word",
          "value": 7
        },
        "Param1": {
          "type": "byte",
          "value": 255
        },
        "Param1Value": {
          "type": "byte",
          "value": 255
        },
        "PropertyName": {
          "type": "word",
          "value": 20
        },
        "Subtype": {
          "type": "word",
          "value": 10
        }
      }
    ]
  },
  "StackSize": {
    "type": "word",
    "value": 1
  },
  "Stolen": {
    "type": "byte",
    "value": 0
  },
  "Tag": {
    "type": "cexostring",
    "value": "M4Q1D08_IMM_FIRE"
  },
  "TemplateResRef": {
    "type": "resref",
    "value": "m4q1d08_imm_fire"
  }
}
