{
  "__data_type": "UTC ",
  "Appearance_Type": {
    "type": "word",
    "value": 301
  },
  "BodyBag": {
    "type": "byte",
    "value": 0
  },
  "Cha": {
    "type": "byte",
    "value": 15
  },
  "ChallengeRating": {
    "type": "float",
    "value": 1.0
  },
  "ClassList": {
    "type": "list",
    "value": [
      {
        "__struct_id": 2,
        "Class": {
          "type": "int",
          "value": 1
        },
        "ClassLevel": {
          "type": "short",
          "value": 1
        }
      }
    ]
  },
  "Comment": {
    "type": "cexostring",
    "value": ""
  },
  "Con": {
    "type": "byte",
    "value": 15
  },
  "Conversation": {
    "type": "resref",
    "value": "xp1_hen_dee"
  },
  "CRAdjust": {
    "type": "int",
    "value": 0
  },
  "CurrentHitPoints": {
    "type": "short",
    "value": 6
  },
  "DecayTime": {
    "type": "dword",
    "value": 0
  },
  "Deity": {
    "type": "cexostring",
    "value": ""
  },
  "Description": {
    "type": "cexolocstring",
    "value": {
      "id": 83037
    }
  },
  "Dex": {
    "type": "byte",
    "value": 12
  },
  "Disarmable": {
    "type": "byte",
    "value": 0
  },
  "Equip_ItemList": {
    "type": "list",
    "value": [
      {
        "__struct_id": 16,
        "EquippedRes": {
          "type": "resref",
          "value": "dee_lxbow"
        }
      },
      {
        "__struct_id": 131072,
        "EquippedRes": {
          "type": "resref",
          "value": "nw_hen_hide"
        }
      }
    ]
  },
  "FactionID": {
    "type": "word",
    "value": 3
  },
  "FeatList": {
    "type": "list",
    "value": [
      {
        "__struct_id": 1,
        "Feat": {
          "type": "word",
          "value": 0
        }
      },
      {
        "__struct_id": 1,
        "Feat": {
          "type": "word",
          "value": 3
        }
      },
      {
        "__struct_id": 1,
        "Feat": {
          "type": "word",
          "value": 4
        }
      },
      {
        "__struct_id": 1,
        "Feat": {
          "type": "word",
          "value": 257
        }
      },
      {
        "__struct_id": 1,
        "Feat": {
          "type": "word",
          "value": 197
        }
      },
      {
        "__struct_id": 1,
        "Feat": {
          "type": "word",
          "value": 228
        }
      },
      {
        "__struct_id": 1,
        "Feat": {
          "type": "word",
          "value": 411
        }
      },
      {
        "__struct_id": 1,
        "Feat": {
          "type": "word",
          "value": 32
        }
      },
      {
        "__struct_id": 1,
        "Feat": {
          "type": "word",
          "value": 289
        }
      },
      {
        "__struct_id": 1,
        "Feat": {
          "type": "word",
          "value": 50
        }
      },
      {
        "__struct_id": 1,
        "Feat": {
          "type": "word",
          "value": 46
        }
      }
    ]
  },
  "FirstName": {
    "type": "cexolocstring",
    "value": {
      "id": 75004
    }
  },
  "fortbonus": {
    "type": "short",
    "value": 0
  },
  "Gender": {
    "type": "byte",
    "value": 0
  },
  "GoodEvil": {
    "type": "byte",
    "value": 100
  },
  "HitPoints": {
    "type": "short",
    "value": 6
  },
  "Int": {
    "type": "byte",
    "value": 10
  },
  "Interruptable": {
    "type": "byte",
    "value": 1
  },
  "IsImmortal": {
    "type": "byte",
    "value": 1
  },
  "IsPC": {
    "type": "byte",
    "value": 0
  },
  "ItemList": {
    "type": "list",
    "value": [
      {
        "__struct_id": 0,
        "InventoryRes": {
          "type": "resref",
          "value": "nw_it_sparscr106"
        },
        "Repos_PosX": {
          "type": "word",
          "value": 0
        },
        "Repos_Posy": {
          "type": "word",
          "value": 0
        }
      },
      {
        "__struct_id": 1,
        "InventoryRes": {
          "type": "resref",
          "value": "nw_wswmdg002"
        },
        "Repos_PosX": {
          "type": "word",
          "value": 1
        },
        "Repos_Posy": {
          "type": "word",
          "value": 0
        }
      },
      {
        "__struct_id": 2,
        "InventoryRes": {
          "type": "resref",
          "value": "nw_it_sparscr304"
        },
        "Repos_PosX": {
          "type": "word",
          "value": 2
        },
        "Repos_Posy": {
          "type": "word",
          "value": 0
        }
      },
      {
        "__struct_id": 3,
        "InventoryRes": {
          "type": "resref",
          "value": "nw_it_sparscr304"
        },
        "Repos_PosX": {
          "type": "word",
          "value": 3
        },
        "Repos_Posy": {
          "type": "word",
          "value": 0
        }
      },
      {
        "__struct_id": 4,
        "InventoryRes": {
          "type": "resref",
          "value": "nw_it_sparscr202"
        },
        "Repos_PosX": {
          "type": "word",
          "value": 4
        },
        "Repos_Posy": {
          "type": "word",
          "value": 0
        }
      },
      {
        "__struct_id": 5,
        "InventoryRes": {
          "type": "resref",
          "value": "nw_it_sparscr312"
        },
        "Repos_PosX": {
          "type": "word",
          "value": 5
        },
        "Repos_Posy": {
          "type": "word",
          "value": 0
        }
      }
    ]
  },
  "LastName": {
    "type": "cexolocstring",
    "value": {}
  },
  "LawfulChaotic": {
    "type": "byte",
    "value": 0
  },
  "Lootable": {
    "type": "byte",
    "value": 0
  },
  "MaxHitPoints": {
    "type": "short",
    "value": 8
  },
  "NaturalAC": {
    "type": "byte",
    "value": 1
  },
  "NoPermDeath": {
    "type": "byte",
    "value": 1
  },
  "PaletteID": {
    "type": "byte",
    "value": 4
  },
  "PerceptionRange": {
    "type": "byte",
    "value": 11
  },
  "Phenotype": {
    "type": "int",
    "value": 0
  },
  "Plot": {
    "type": "byte",
    "value": 0
  },
  "PortraitId": {
    "type": "word",
    "value": 650
  },
  "Race": {
    "type": "byte",
    "value": 15
  },
  "refbonus": {
    "type": "short",
    "value": 0
  },
  "ScriptAttacked": {
    "type": "resref",
    "value": "x0_ch_hen_attack"
  },
  "ScriptDamaged": {
    "type": "resref",
    "value": "x0_ch_hen_damage"
  },
  "ScriptDeath": {
    "type": "resref",
    "value": "x0_ch_hen_death"
  },
  "ScriptDialogue": {
    "type": "resref",
    "value": "x0_ch_hen_conv"
  },
  "ScriptDisturbed": {
    "type": "resref",
    "value": "x0_ch_hen_distrb"
  },
  "ScriptEndRound": {
    "type": "resref",
    "value": "x0_ch_hen_combat"
  },
  "ScriptHeartbeat": {
    "type": "resref",
    "value": "x0_ch_hen_heart"
  },
  "ScriptOnBlocked": {
    "type": "resref",
    "value": "x0_ch_hen_block"
  },
  "ScriptOnNotice": {
    "type": "resref",
    "value": "x0_ch_hen_percep"
  },
  "ScriptRested": {
    "type": "resref",
    "value": "x0_ch_hen_rest"
  },
  "ScriptSpawn": {
    "type": "resref",
    "value": "x0_ch_hen_spawn"
  },
  "ScriptSpellAt": {
    "type": "resref",
    "value": "x0_ch_hen_spell"
  },
  "ScriptUserDefine": {
    "type": "resref",
    "value": "x0_ch_hen_usrdef"
  },
  "SkillList": {
    "type": "list",
    "value": [
      {
        "__struct_id": 0,
        "Rank": {
          "type": "byte",
          "value": 0
        }
      },
      {
        "__struct_id": 0,
        "Rank": {
          "type": "byte",
          "value": 3
        }
      },
      {
        "__struct_id": 0,
        "Rank": {
          "type": "byte",
          "value": 0
        }
      },
      {
        "__struct_id": 0,
        "Rank": {
          "type": "byte",
          "value": 0
        }
      },
      {
        "__struct_id": 0,
        "Rank": {
          "type": "byte",
          "value": 0
        }
      },
      {
        "__struct_id": 0,
        "Rank": {
          "type": "byte",
          "value": 8
        }
      },
      {
        "__struct_id": 0,
        "Rank": {
          "type": "byte",
          "value": 2
        }
      },
      {
        "__struct_id": 0,
        "Rank": {
          "type": "byte",
          "value": 4
        }
      },
      {
        "__struct_id": 0,
        "Rank": {
          "type": "byte",
          "value": 4
        }
      },
      {
        "__struct_id": 0,
        "Rank": {
          "type": "byte",
          "value": 0
        }
      },
      {
        "__struct_id": 0,
        "Rank": {
          "type": "byte",
          "value": 0
        }
      },
      {
        "__struct_id": 0,
        "Rank": {
          "type": "byte",
          "value": 4
        }
      },
      {
        "__struct_id": 0,
        "Rank": {
          "type": "byte",
          "value": 0
        }
      },
      {
        "__struct_id": 0,
        "Rank": {
          "type": "byte",
          "value": 0
        }
      },
      {
        "__struct_id": 0,
        "Rank": {
          "type": "byte",
          "value": 2
        }
      },
      {
        "__struct_id": 0,
        "Rank": {
          "type": "byte",
          "value": 0
        }
      },
      {
        "__struct_id": 0,
        "Rank": {
          "type": "byte",
          "value": 1
        }
      },
      {
        "__struct_id": 0,
        "Rank": {
          "type": "byte",
          "value": 2
        }
      },
      {
        "__struct_id": 0,
        "Rank": {
          "type": "byte",
          "value": 0
        }
      },
      {
        "__struct_id": 0,
        "Rank": {
          "type": "byte",
          "value": 2
        }
      },
      {
        "__struct_id": 0,
        "Rank": {
          "type": "byte",
          "value": 0
        }
      },
      {
        "__struct_id": 0,
        "Rank": {
          "type": "byte",
          "value": 0
        }
      },
      {
        "__struct_id": 0,
        "Rank": {
          "type": "byte",
          "value": 2
        }
      },
      {
        "__struct_id": 0,
        "Rank": {
          "type": "byte",
          "value": 0
        }
      },
      {
        "__struct_id": 0,
        "Rank": {
          "type": "byte",
          "value": 0
        }
      },
      {
        "__struct_id": 0,
        "Rank": {
          "type": "byte",
          "value": 0
        }
      },
      {
        "__struct_id": 0,
        "Rank": {
          "type": "byte",
          "value": 0
        }
      },
      {
        "__struct_id": 0,
        "Rank": {
          "type": "byte",
          "value": 0
        }
      }
    ]
  },
  "SoundSetFile": {
    "type": "word",
    "value": 346
  },
  "SpecAbilityList": {
    "type": "list",
    "value": []
  },
  "StartingPackage": {
    "type": "byte",
    "value": 72
  },
  "Str": {
    "type": "byte",
    "value": 6
  },
  "Subrace": {
    "type": "cexostring",
    "value": ""
  },
  "Tag": {
    "type": "cexostring",
    "value": "x0_hen_dee"
  },
  "Tail_New": {
    "type": "dword",
    "value": 0
  },
  "TemplateList": {
    "type": "list",
    "value": []
  },
  "TemplateResRef": {
    "type": "resref",
    "value": "x0_hen_dee"
  },
  "WalkRate": {
    "type": "int",
    "value": 4
  },
  "willbonus": {
    "type": "short",
    "value": 0
  },
  "Wings_New": {
    "type": "dword",
    "value": 0
  },
  "Wis": {
    "type": "byte",
    "value": 10
  }
}
