{
  "__data_type": "DLG ",
  "DelayEntry": {
    "type": "dword",
    "value": 0
  },
  "DelayReply": {
    "type": "dword",
    "value": 0
  },
  "EndConverAbort": {
    "type": "resref",
    "value": "q1h_endcon_abkob"
  },
  "EndConversation": {
    "type": "resref",
    "value": ""
  },
  "EntryList": {
    "type": "list",
    "value": [
      {
        "__struct_id": 0,
        "Animation": {
          "type": "dword",
          "value": 0
        },
        "AnimLoop": {
          "type": "byte",
          "value": 1
        },
        "Comment": {
          "type": "cexostring",
          "value": ""
        },
        "Delay": {
          "type": "dword",
          "value": 4294967295
        },
        "Quest": {
          "type": "cexostring",
          "value": ""
        },
        "RepliesList": {
          "type": "list",
          "value": [
            {
              "__struct_id": 0,
              "Active": {
                "type": "resref",
                "value": "x1_chk_gems"
              },
              "Index": {
                "type": "dword",
                "value": 19
              },
              "IsChild": {
                "type": "byte",
                "value": 1
              },
              "LinkComment": {
                "type": "cexostring",
                "value": ""
              }
            },
            {
              "__struct_id": 1,
              "Active": {
                "type": "resref",
                "value": "con_q1hkobold_1"
              },
              "Index": {
                "type": "dword",
                "value": 12
              },
              "IsChild": {
                "type": "byte",
                "value": 1
              },
              "LinkComment": {
                "type": "cexostring",
                "value": ""
              }
            },
            {
              "__struct_id": 2,
              "Active": {
                "type": "resref",
                "value": ""
              },
              "Index": {
                "type": "dword",
                "value": 11
              },
              "IsChild": {
                "type": "byte",
                "value": 1
              },
              "LinkComment": {
                "type": "cexostring",
                "value": ""
              }
            },
            {
              "__struct_id": 3,
              "Active": {
                "type": "resref",
                "value": ""
              },
              "Index": {
                "type": "dword",
                "value": 17
              },
              "IsChild": {
                "type": "byte",
                "value": 1
              },
              "LinkComment": {
                "type": "cexostring",
                "value": ""
              }
            },
            {
              "__struct_id": 4,
              "Active": {
                "type": "resref",
                "value": ""
              },
              "Index": {
                "type": "dword",
                "value": 10
              },
              "IsChild": {
                "type": "byte",
                "value": 1
              },
              "LinkComment": {
                "type": "cexostring",
                "value": ""
              }
            }
          ]
        },
        "Script": {
          "type": "resref",
          "value": ""
        },
        "Sound": {
          "type": "resref",
          "value": ""
        },
        "Speaker": {
          "type": "cexostring",
          "value": ""
        },
        "Text": {
          "type": "cexolocstring",
          "value": {
            "id": 70904
          }
        }
      },
      {
        "__struct_id": 1,
        "Animation": {
          "type": "dword",
          "value": 44
        },
        "AnimLoop": {
          "type": "byte",
          "value": 0
        },
        "Comment": {
          "type": "cexostring",
          "value": ""
        },
        "Delay": {
          "type": "dword",
          "value": 4294967295
        },
        "Quest": {
          "type": "cexostring",
          "value": "q1bfamily"
        },
        "QuestEntry": {
          "type": "dword",
          "value": 10
        },
        "RepliesList": {
          "type": "list",
          "value": [
            {
              "__struct_id": 0,
              "Active": {
                "type": "resref",
                "value": ""
              },
              "Index": {
                "type": "dword",
                "value": 2
              },
              "IsChild": {
                "type": "byte",
                "value": 0
              }
            },
            {
              "__struct_id": 1,
              "Active": {
                "type": "resref",
                "value": ""
              },
              "Index": {
                "type": "dword",
                "value": 1
              },
              "IsChild": {
                "type": "byte",
                "value": 0
              }
            },
            {
              "__struct_id": 2,
              "Active": {
                "type": "resref",
                "value": ""
              },
              "Index": {
                "type": "dword",
                "value": 0
              },
              "IsChild": {
                "type": "byte",
                "value": 0
              }
            }
          ]
        },
        "Script": {
          "type": "resref",
          "value": ""
        },
        "Sound": {
          "type": "resref",
          "value": ""
        },
        "Speaker": {
          "type": "cexostring",
          "value": ""
        },
        "Text": {
          "type": "cexolocstring",
          "value": {
            "id": 70905
          }
        }
      },
      {
        "__struct_id": 2,
        "Animation": {
          "type": "dword",
          "value": 0
        },
        "AnimLoop": {
          "type": "byte",
          "value": 1
        },
        "Comment": {
          "type": "cexostring",
          "value": ""
        },
        "Delay": {
          "type": "dword",
          "value": 4294967295
        },
        "Quest": {
          "type": "cexostring",
          "value": ""
        },
        "RepliesList": {
          "type": "list",
          "value": [
            {
              "__struct_id": 0,
              "Active": {
                "type": "resref",
                "value": ""
              },
              "Index": {
                "type": "dword",
                "value": 3
              },
              "IsChild": {
                "type": "byte",
                "value": 0
              }
            }
          ]
        },
        "Script": {
          "type": "resref",
          "value": "act_q1hkobold_6"
        },
        "Sound": {
          "type": "resref",
          "value": ""
        },
        "Speaker": {
          "type": "cexostring",
          "value": ""
        },
        "Text": {
          "type": "cexolocstring",
          "value": {
            "id": 70906
          }
        }
      },
      {
        "__struct_id": 3,
        "Animation": {
          "type": "dword",
          "value": 0
        },
        "AnimLoop": {
          "type": "byte",
          "value": 1
        },
        "Comment": {
          "type": "cexostring",
          "value": ""
        },
        "Delay": {
          "type": "dword",
          "value": 4294967295
        },
        "Quest": {
          "type": "cexostring",
          "value": ""
        },
        "RepliesList": {
          "type": "list",
          "value": [
            {
              "__struct_id": 0,
              "Active": {
                "type": "resref",
                "value": "x1_chk_gems"
              },
              "Index": {
                "type": "dword",
                "value": 19
              },
              "IsChild": {
                "type": "byte",
                "value": 0
              }
            },
            {
              "__struct_id": 1,
              "Active": {
                "type": "resref",
                "value": ""
              },
              "Index": {
                "type": "dword",
                "value": 17
              },
              "IsChild": {
                "type": "byte",
                "value": 0
              }
            },
            {
              "__struct_id": 2,
              "Active": {
                "type": "resref",
                "value": "con_q1hkobold_1"
              },
              "Index": {
                "type": "dword",
                "value": 12
              },
              "IsChild": {
                "type": "byte",
                "value": 0
              }
            },
            {
              "__struct_id": 3,
              "Active": {
                "type": "resref",
                "value": ""
              },
              "Index": {
                "type": "dword",
                "value": 11
              },
              "IsChild": {
                "type": "byte",
                "value": 0
              }
            },
            {
              "__struct_id": 4,
              "Active": {
                "type": "resref",
                "value": ""
              },
              "Index": {
                "type": "dword",
                "value": 10
              },
              "IsChild": {
                "type": "byte",
                "value": 0
              }
            },
            {
              "__struct_id": 5,
              "Active": {
                "type": "resref",
                "value": "xp1_checkcharm"
              },
              "Index": {
                "type": "dword",
                "value": 7
              },
              "IsChild": {
                "type": "byte",
                "value": 0
              }
            },
            {
              "__struct_id": 6,
              "Active": {
                "type": "resref",
                "value": "xp1_pcisbard"
              },
              "Index": {
                "type": "dword",
                "value": 4
              },
              "IsChild": {
                "type": "byte",
                "value": 0
              }
            }
          ]
        },
        "Script": {
          "type": "resref",
          "value": ""
        },
        "Sound": {
          "type": "resref",
          "value": ""
        },
        "Speaker": {
          "type": "cexostring",
          "value": ""
        },
        "Text": {
          "type": "cexolocstring",
          "value": {
            "id": 70907
          }
        }
      },
      {
        "__struct_id": 4,
        "Animation": {
          "type": "dword",
          "value": 0
        },
        "AnimLoop": {
          "type": "byte",
          "value": 1
        },
        "Comment": {
          "type": "cexostring",
          "value": ""
        },
        "Delay": {
          "type": "dword",
          "value": 4294967295
        },
        "Quest": {
          "type": "cexostring",
          "value": ""
        },
        "RepliesList": {
          "type": "list",
          "value": [
            {
              "__struct_id": 0,
              "Active": {
                "type": "resref",
                "value": ""
              },
              "Index": {
                "type": "dword",
                "value": 5
              },
              "IsChild": {
                "type": "byte",
                "value": 0
              }
            }
          ]
        },
        "Script": {
          "type": "resref",
          "value": ""
        },
        "Sound": {
          "type": "resref",
          "value": ""
        },
        "Speaker": {
          "type": "cexostring",
          "value": ""
        },
        "Text": {
          "type": "cexolocstring",
          "value": {
            "id": 70908
          }
        }
      },
      {
        "__struct_id": 5,
        "Animation": {
          "type": "dword",
          "value": 0
        },
        "AnimLoop": {
          "type": "byte",
          "value": 1
        },
        "Comment": {
          "type": "cexostring",
          "value": ""
        },
        "Delay": {
          "type": "dword",
          "value": 4294967295
        },
        "Quest": {
          "type": "cexostring",
          "value": ""
        },
        "RepliesList": {
          "type": "list",
          "value": [
            {
              "__struct_id": 0,
              "Active": {
                "type": "resref",
                "value": ""
              },
              "Index": {
                "type": "dword",
                "value": 6
              },
              "IsChild": {
                "type": "byte",
                "value": 0
              }
            }
          ]
        },
        "Script": {
          "type": "resref",
          "value": "act_q1hkobold_1"
        },
        "Sound": {
          "type": "resref",
          "value": ""
        },
        "Speaker": {
          "type": "cexostring",
          "value": ""
        },
        "Text": {
          "type": "cexolocstring",
          "value": {
            "id": 70909
          }
        }
      },
      {
        "__struct_id": 6,
        "Animation": {
          "type": "dword",
          "value": 0
        },
        "AnimLoop": {
          "type": "byte",
          "value": 1
        },
        "Comment": {
          "type": "cexostring",
          "value": ""
        },
        "Delay": {
          "type": "dword",
          "value": 4294967295
        },
        "Quest": {
          "type": "cexostring",
          "value": ""
        },
        "RepliesList": {
          "type": "list",
          "value": [
            {
              "__struct_id": 0,
              "Active": {
                "type": "resref",
                "value": ""
              },
              "Index": {
                "type": "dword",
                "value": 8
              },
              "IsChild": {
                "type": "byte",
                "value": 0
              }
            }
          ]
        },
        "Script": {
          "type": "resref",
          "value": "act_q1hkobold_1"
        },
        "Sound": {
          "type": "resref",
          "value": ""
        },
        "Speaker": {
          "type": "cexostring",
          "value": ""
        },
        "Text": {
          "type": "cexolocstring",
          "value": {
            "id": 70910
          }
        }
      },
      {
        "__struct_id": 7,
        "Animation": {
          "type": "dword",
          "value": 0
        },
        "AnimLoop": {
          "type": "byte",
          "value": 1
        },
        "Comment": {
          "type": "cexostring",
          "value": ""
        },
        "Delay": {
          "type": "dword",
          "value": 4294967295
        },
        "Quest": {
          "type": "cexostring",
          "value": ""
        },
        "RepliesList": {
          "type": "list",
          "value": [
            {
              "__struct_id": 0,
              "Active": {
                "type": "resref",
                "value": ""
              },
              "Index": {
                "type": "dword",
                "value": 9
              },
              "IsChild": {
                "type": "byte",
                "value": 0
              }
            }
          ]
        },
        "Script": {
          "type": "resref",
          "value": "act_q1hkobold_10"
        },
        "Sound": {
          "type": "resref",
          "value": ""
        },
        "Speaker": {
          "type": "cexostring",
          "value": ""
        },
        "Text": {
          "type": "cexolocstring",
          "value": {
            "id": 70911
          }
        }
      },
      {
        "__struct_id": 8,
        "Animation": {
          "type": "dword",
          "value": 0
        },
        "AnimLoop": {
          "type": "byte",
          "value": 1
        },
        "Comment": {
          "type": "cexostring",
          "value": ""
        },
        "Delay": {
          "type": "dword",
          "value": 4294967295
        },
        "Quest": {
          "type": "cexostring",
          "value": ""
        },
        "RepliesList": {
          "type": "list",
          "value": [
            {
              "__struct_id": 0,
              "Active": {
                "type": "resref",
                "value": "x1_chk_gems"
              },
              "Index": {
                "type": "dword",
                "value": 19
              },
              "IsChild": {
                "type": "byte",
                "value": 1
              },
              "LinkComment": {
                "type": "cexostring",
                "value": ""
              }
            },
            {
              "__struct_id": 1,
              "Active": {
                "type": "resref",
                "value": ""
              },
              "Index": {
                "type": "dword",
                "value": 11
              },
              "IsChild": {
                "type": "byte",
                "value": 1
              },
              "LinkComment": {
                "type": "cexostring",
                "value": ""
              }
            },
            {
              "__struct_id": 2,
              "Active": {
                "type": "resref",
                "value": ""
              },
              "Index": {
                "type": "dword",
                "value": 17
              },
              "IsChild": {
                "type": "byte",
                "value": 1
              },
              "LinkComment": {
                "type": "cexostring",
                "value": ""
              }
            },
            {
              "__struct_id": 3,
              "Active": {
                "type": "resref",
                "value": "con_q1hkobold_1"
              },
              "Index": {
                "type": "dword",
                "value": 12
              },
              "IsChild": {
                "type": "byte",
                "value": 1
              },
              "LinkComment": {
                "type": "cexostring",
                "value": ""
              }
            }
          ]
        },
        "Script": {
          "type": "resref",
          "value": ""
        },
        "Sound": {
          "type": "resref",
          "value": ""
        },
        "Speaker": {
          "type": "cexostring",
          "value": ""
        },
        "Text": {
          "type": "cexolocstring",
          "value": {
            "id": 70912
          }
        }
      },
      {
        "__struct_id": 9,
        "Animation": {
          "type": "dword",
          "value": 0
        },
        "AnimLoop": {
          "type": "byte",
          "value": 1
        },
        "Comment": {
          "type": "cexostring",
          "value": ""
        },
        "Delay": {
          "type": "dword",
          "value": 4294967295
        },
        "Quest": {
          "type": "cexostring",
          "value": ""
        },
        "RepliesList": {
          "type": "list",
          "value": [
            {
              "__struct_id": 0,
              "Active": {
                "type": "resref",
                "value": ""
              },
              "Index": {
                "type": "dword",
                "value": 15
              },
              "IsChild": {
                "type": "byte",
                "value": 0
              }
            },
            {
              "__struct_id": 1,
              "Active": {
                "type": "resref",
                "value": ""
              },
              "Index": {
                "type": "dword",
                "value": 14
              },
              "IsChild": {
                "type": "byte",
                "value": 0
              }
            },
            {
              "__struct_id": 2,
              "Active": {
                "type": "resref",
                "value": ""
              },
              "Index": {
                "type": "dword",
                "value": 13
              },
              "IsChild": {
                "type": "byte",
                "value": 0
              }
            }
          ]
        },
        "Script": {
          "type": "resref",
          "value": "act_q1hkobold_5"
        },
        "Sound": {
          "type": "resref",
          "value": ""
        },
        "Speaker": {
          "type": "cexostring",
          "value": ""
        },
        "Text": {
          "type": "cexolocstring",
          "value": {
            "id": 70913
          }
        }
      },
      {
        "__struct_id": 10,
        "Animation": {
          "type": "dword",
          "value": 0
        },
        "AnimLoop": {
          "type": "byte",
          "value": 1
        },
        "Comment": {
          "type": "cexostring",
          "value": ""
        },
        "Delay": {
          "type": "dword",
          "value": 4294967295
        },
        "Quest": {
          "type": "cexostring",
          "value": ""
        },
        "RepliesList": {
          "type": "list",
          "value": [
            {
              "__struct_id": 0,
              "Active": {
                "type": "resref",
                "value": ""
              },
              "Index": {
                "type": "dword",
                "value": 16
              },
              "IsChild": {
                "type": "byte",
                "value": 0
              }
            }
          ]
        },
        "Script": {
          "type": "resref",
          "value": "act_q1hkobold_8"
        },
        "Sound": {
          "type": "resref",
          "value": ""
        },
        "Speaker": {
          "type": "cexostring",
          "value": ""
        },
        "Text": {
          "type": "cexolocstring",
          "value": {
            "id": 70914
          }
        }
      },
      {
        "__struct_id": 11,
        "Animation": {
          "type": "dword",
          "value": 0
        },
        "AnimLoop": {
          "type": "byte",
          "value": 1
        },
        "Comment": {
          "type": "cexostring",
          "value": ""
        },
        "Delay": {
          "type": "dword",
          "value": 4294967295
        },
        "Quest": {
          "type": "cexostring",
          "value": ""
        },
        "RepliesList": {
          "type": "list",
          "value": [
            {
              "__struct_id": 0,
              "Active": {
                "type": "resref",
                "value": ""
              },
              "Index": {
                "type": "dword",
                "value": 18
              },
              "IsChild": {
                "type": "byte",
                "value": 0
              }
            }
          ]
        },
        "Script": {
          "type": "resref",
          "value": ""
        },
        "Sound": {
          "type": "resref",
          "value": ""
        },
        "Speaker": {
          "type": "cexostring",
          "value": ""
        },
        "Text": {
          "type": "cexolocstring",
          "value": {
            "id": 70915
          }
        }
      },
      {
        "__struct_id": 12,
        "Animation": {
          "type": "dword",
          "value": 0
        },
        "AnimLoop": {
          "type": "byte",
          "value": 1
        },
        "Comment": {
          "type": "cexostring",
          "value": ""
        },
        "Delay": {
          "type": "dword",
          "value": 4294967295
        },
        "Quest": {
          "type": "cexostring",
          "value": ""
        },
        "RepliesList": {
          "type": "list",
          "value": [
            {
              "__struct_id": 0,
              "Active": {
                "type": "resref",
                "value": ""
              },
              "Index": {
                "type": "dword",
                "value": 20
              },
              "IsChild": {
                "type": "byte",
                "value": 0
              }
            }
          ]
        },
        "Script": {
          "type": "resref",
          "value": "act_q1hkobold_3"
        },
        "Sound": {
          "type": "resref",
          "value": "vs_nx0deekm_haha"
        },
        "Speaker": {
          "type": "cexostring",
          "value": ""
        },
        "Text": {
          "type": "cexolocstring",
          "value": {
            "id": 70916
          }
        }
      },
      {
        "__struct_id": 13,
        "Animation": {
          "type": "dword",
          "value": 0
        },
        "AnimLoop": {
          "type": "byte",
          "value": 1
        },
        "Comment": {
          "type": "cexostring",
          "value": ""
        },
        "Delay": {
          "type": "dword",
          "value": 4294967295
        },
        "Quest": {
          "type": "cexostring",
          "value": ""
        },
        "RepliesList": {
          "type": "list",
          "value": [
            {
              "__struct_id": 0,
              "Active": {
                "type": "resref",
                "value": ""
              },
              "Index": {
                "type": "dword",
                "value": 28
              },
              "IsChild": {
                "type": "byte",
                "value": 0
              }
            },
            {
              "__struct_id": 1,
              "Active": {
                "type": "resref",
                "value": ""
              },
              "Index": {
                "type": "dword",
                "value": 27
              },
              "IsChild": {
                "type": "byte",
                "value": 0
              }
            },
            {
              "__struct_id": 2,
              "Active": {
                "type": "resref",
                "value": ""
              },
              "Index": {
                "type": "dword",
                "value": 24
              },
              "IsChild": {
                "type": "byte",
                "value": 0
              }
            },
            {
              "__struct_id": 3,
              "Active": {
                "type": "resref",
                "value": ""
              },
              "Index": {
                "type": "dword",
                "value": 23
              },
              "IsChild": {
                "type": "byte",
                "value": 0
              }
            },
            {
              "__struct_id": 4,
              "Active": {
                "type": "resref",
                "value": ""
              },
              "Index": {
                "type": "dword",
                "value": 21
              },
              "IsChild": {
                "type": "byte",
                "value": 0
              }
            }
          ]
        },
        "Script": {
          "type": "resref",
          "value": ""
        },
        "Sound": {
          "type": "resref",
          "value": ""
        },
        "Speaker": {
          "type": "cexostring",
          "value": "q1hblake"
        },
        "Text": {
          "type": "cexolocstring",
          "value": {
            "id": 70917
          }
        }
      },
      {
        "__struct_id": 14,
        "Animation": {
          "type": "dword",
          "value": 0
        },
        "AnimLoop": {
          "type": "byte",
          "value": 1
        },
        "Comment": {
          "type": "cexostring",
          "value": ""
        },
        "Delay": {
          "type": "dword",
          "value": 4294967295
        },
        "Quest": {
          "type": "cexostring",
          "value": ""
        },
        "RepliesList": {
          "type": "list",
          "value": [
            {
              "__struct_id": 0,
              "Active": {
                "type": "resref",
                "value": ""
              },
              "Index": {
                "type": "dword",
                "value": 22
              },
              "IsChild": {
                "type": "byte",
                "value": 0
              }
            }
          ]
        },
        "Script": {
          "type": "resref",
          "value": "act_q1hkobold_2"
        },
        "Sound": {
          "type": "resref",
          "value": ""
        },
        "Speaker": {
          "type": "cexostring",
          "value": ""
        },
        "Text": {
          "type": "cexolocstring",
          "value": {
            "id": 70918
          }
        }
      },
      {
        "__struct_id": 15,
        "Animation": {
          "type": "dword",
          "value": 0
        },
        "AnimLoop": {
          "type": "byte",
          "value": 1
        },
        "Comment": {
          "type": "cexostring",
          "value": ""
        },
        "Delay": {
          "type": "dword",
          "value": 4294967295
        },
        "Quest": {
          "type": "cexostring",
          "value": ""
        },
        "RepliesList": {
          "type": "list",
          "value": [
            {
              "__struct_id": 0,
              "Active": {
                "type": "resref",
                "value": ""
              },
              "Index": {
                "type": "dword",
                "value": 25
              },
              "IsChild": {
                "type": "byte",
                "value": 0
              }
            },
            {
              "__struct_id": 1,
              "Active": {
                "type": "resref",
                "value": ""
              },
              "Index": {
                "type": "dword",
                "value": 27
              },
              "IsChild": {
                "type": "byte",
                "value": 1
              },
              "LinkComment": {
                "type": "cexostring",
                "value": ""
              }
            },
            {
              "__struct_id": 2,
              "Active": {
                "type": "resref",
                "value": ""
              },
              "Index": {
                "type": "dword",
                "value": 23
              },
              "IsChild": {
                "type": "byte",
                "value": 1
              },
              "LinkComment": {
                "type": "cexostring",
                "value": ""
              }
            },
            {
              "__struct_id": 3,
              "Active": {
                "type": "resref",
                "value": ""
              },
              "Index": {
                "type": "dword",
                "value": 21
              },
              "IsChild": {
                "type": "byte",
                "value": 1
              },
              "LinkComment": {
                "type": "cexostring",
                "value": ""
              }
            }
          ]
        },
        "Script": {
          "type": "resref",
          "value": ""
        },
        "Sound": {
          "type": "resref",
          "value": ""
        },
        "Speaker": {
          "type": "cexostring",
          "value": "q1hblake"
        },
        "Text": {
          "type": "cexolocstring",
          "value": {
            "id": 70919
          }
        }
      },
      {
        "__struct_id": 16,
        "Animation": {
          "type": "dword",
          "value": 0
        },
        "AnimLoop": {
          "type": "byte",
          "value": 1
        },
        "Comment": {
          "type": "cexostring",
          "value": ""
        },
        "Delay": {
          "type": "dword",
          "value": 4294967295
        },
        "Quest": {
          "type": "cexostring",
          "value": ""
        },
        "RepliesList": {
          "type": "list",
          "value": [
            {
              "__struct_id": 0,
              "Active": {
                "type": "resref",
                "value": ""
              },
              "Index": {
                "type": "dword",
                "value": 26
              },
              "IsChild": {
                "type": "byte",
                "value": 0
              }
            }
          ]
        },
        "Script": {
          "type": "resref",
          "value": ""
        },
        "Sound": {
          "type": "resref",
          "value": ""
        },
        "Speaker": {
          "type": "cexostring",
          "value": "q1hblake"
        },
        "Text": {
          "type": "cexolocstring",
          "value": {
            "id": 70920
          }
        }
      },
      {
        "__struct_id": 17,
        "Animation": {
          "type": "dword",
          "value": 0
        },
        "AnimLoop": {
          "type": "byte",
          "value": 1
        },
        "Comment": {
          "type": "cexostring",
          "value": ""
        },
        "Delay": {
          "type": "dword",
          "value": 4294967295
        },
        "Quest": {
          "type": "cexostring",
          "value": ""
        },
        "RepliesList": {
          "type": "list",
          "value": [
            {
              "__struct_id": 0,
              "Active": {
                "type": "resref",
                "value": ""
              },
              "Index": {
                "type": "dword",
                "value": 17
              },
              "IsChild": {
                "type": "byte",
                "value": 1
              },
              "LinkComment": {
                "type": "cexostring",
                "value": ""
              }
            },
            {
              "__struct_id": 1,
              "Active": {
                "type": "resref",
                "value": ""
              },
              "Index": {
                "type": "dword",
                "value": 23
              },
              "IsChild": {
                "type": "byte",
                "value": 1
              },
              "LinkComment": {
                "type": "cexostring",
                "value": ""
              }
            },
            {
              "__struct_id": 2,
              "Active": {
                "type": "resref",
                "value": ""
              },
              "Index": {
                "type": "dword",
                "value": 21
              },
              "IsChild": {
                "type": "byte",
                "value": 1
              },
              "LinkComment": {
                "type": "cexostring",
                "value": ""
              }
            }
          ]
        },
        "Script": {
          "type": "resref",
          "value": ""
        },
        "Sound": {
          "type": "resref",
          "value": ""
        },
        "Speaker": {
          "type": "cexostring",
          "value": ""
        },
        "Text": {
          "type": "cexolocstring",
          "value": {
            "id": 70921
          }
        }
      },
      {
        "__struct_id": 18,
        "Animation": {
          "type": "dword",
          "value": 0
        },
        "AnimLoop": {
          "type": "byte",
          "value": 1
        },
        "Comment": {
          "type": "cexostring",
          "value": ""
        },
        "Delay": {
          "type": "dword",
          "value": 4294967295
        },
        "Quest": {
          "type": "cexostring",
          "value": ""
        },
        "RepliesList": {
          "type": "list",
          "value": [
            {
              "__struct_id": 0,
              "Active": {
                "type": "resref",
                "value": ""
              },
              "Index": {
                "type": "dword",
                "value": 28
              },
              "IsChild": {
                "type": "byte",
                "value": 1
              },
              "LinkComment": {
                "type": "cexostring",
                "value": ""
              }
            },
            {
              "__struct_id": 1,
              "Active": {
                "type": "resref",
                "value": ""
              },
              "Index": {
                "type": "dword",
                "value": 24
              },
              "IsChild": {
                "type": "byte",
                "value": 1
              },
              "LinkComment": {
                "type": "cexostring",
                "value": ""
              }
            },
            {
              "__struct_id": 2,
              "Active": {
                "type": "resref",
                "value": ""
              },
              "Index": {
                "type": "dword",
                "value": 23
              },
              "IsChild": {
                "type": "byte",
                "value": 1
              },
              "LinkComment": {
                "type": "cexostring",
                "value": ""
              }
            },
            {
              "__struct_id": 3,
              "Active": {
                "type": "resref",
                "value": ""
              },
              "Index": {
                "type": "dword",
                "value": 21
              },
              "IsChild": {
                "type": "byte",
                "value": 1
              },
              "LinkComment": {
                "type": "cexostring",
                "value": ""
              }
            }
          ]
        },
        "Script": {
          "type": "resref",
          "value": ""
        },
        "Sound": {
          "type": "resref",
          "value": ""
        },
        "Speaker": {
          "type": "cexostring",
          "value": "q1hblake"
        },
        "Text": {
          "type": "cexolocstring",
          "value": {
            "id": 70922
          }
        }
      },
      {
        "__struct_id": 19,
        "Animation": {
          "type": "dword",
          "value": 0
        },
        "AnimLoop": {
          "type": "byte",
          "value": 1
        },
        "Comment": {
          "type": "cexostring",
          "value": ""
        },
        "Delay": {
          "type": "dword",
          "value": 4294967295
        },
        "Quest": {
          "type": "cexostring",
          "value": ""
        },
        "RepliesList": {
          "type": "list",
          "value": [
            {
              "__struct_id": 0,
              "Active": {
                "type": "resref",
                "value": ""
              },
              "Index": {
                "type": "dword",
                "value": 29
              },
              "IsChild": {
                "type": "byte",
                "value": 0
              }
            }
          ]
        },
        "Script": {
          "type": "resref",
          "value": ""
        },
        "Sound": {
          "type": "resref",
          "value": ""
        },
        "Speaker": {
          "type": "cexostring",
          "value": "q1hblake"
        },
        "Text": {
          "type": "cexolocstring",
          "value": {
            "id": 70923
          }
        }
      },
      {
        "__struct_id": 20,
        "Animation": {
          "type": "dword",
          "value": 0
        },
        "AnimLoop": {
          "type": "byte",
          "value": 1
        },
        "Comment": {
          "type": "cexostring",
          "value": ""
        },
        "Delay": {
          "type": "dword",
          "value": 4294967295
        },
        "Quest": {
          "type": "cexostring",
          "value": ""
        },
        "RepliesList": {
          "type": "list",
          "value": [
            {
              "__struct_id": 0,
              "Active": {
                "type": "resref",
                "value": ""
              },
              "Index": {
                "type": "dword",
                "value": 30
              },
              "IsChild": {
                "type": "byte",
                "value": 0
              }
            }
          ]
        },
        "Script": {
          "type": "resref",
          "value": ""
        },
        "Sound": {
          "type": "resref",
          "value": ""
        },
        "Speaker": {
          "type": "cexostring",
          "value": ""
        },
        "Text": {
          "type": "cexolocstring",
          "value": {
            "id": 70924
          }
        }
      },
      {
        "__struct_id": 21,
        "Animation": {
          "type": "dword",
          "value": 0
        },
        "AnimLoop": {
          "type": "byte",
          "value": 1
        },
        "Comment": {
          "type": "cexostring",
          "value": ""
        },
        "Delay": {
          "type": "dword",
          "value": 4294967295
        },
        "Quest": {
          "type": "cexostring",
          "value": ""
        },
        "RepliesList": {
          "type": "list",
          "value": [
            {
              "__struct_id": 0,
              "Active": {
                "type": "resref",
                "value": ""
              },
              "Index": {
                "type": "dword",
                "value": 31
              },
              "IsChild": {
                "type": "byte",
                "value": 0
              }
            }
          ]
        },
        "Script": {
          "type": "resref",
          "value": ""
        },
        "Sound": {
          "type": "resref",
          "value": ""
        },
        "Speaker": {
          "type": "cexostring",
          "value": "q1hblake"
        },
        "Text": {
          "type": "cexolocstring",
          "value": {
            "id": 70925
          }
        }
      },
      {
        "__struct_id": 22,
        "Animation": {
          "type": "dword",
          "value": 0
        },
        "AnimLoop": {
          "type": "byte",
          "value": 1
        },
        "Comment": {
          "type": "cexostring",
          "value": ""
        },
        "Delay": {
          "type": "dword",
          "value": 4294967295
        },
        "Quest": {
          "type": "cexostring",
          "value": ""
        },
        "RepliesList": {
          "type": "list",
          "value": [
            {
              "__struct_id": 0,
              "Active": {
                "type": "resref",
                "value": ""
              },
              "Index": {
                "type": "dword",
                "value": 32
              },
              "IsChild": {
                "type": "byte",
                "value": 0
              }
            }
          ]
        },
        "Script": {
          "type": "resref",
          "value": "act_q1hkobold_8"
        },
        "Sound": {
          "type": "resref",
          "value": ""
        },
        "Speaker": {
          "type": "cexostring",
          "value": ""
        },
        "Text": {
          "type": "cexolocstring",
          "value": {
            "id": 70926
          }
        }
      }
    ]
  },
  "NumWords": {
    "type": "dword",
    "value": 488
  },
  "PreventZoomIn": {
    "type": "byte",
    "value": 0
  },
  "ReplyList": {
    "type": "list",
    "value": [
      {
        "__struct_id": 0,
        "Animation": {
          "type": "dword",
          "value": 0
        },
        "AnimLoop": {
          "type": "byte",
          "value": 1
        },
        "Comment": {
          "type": "cexostring",
          "value": ""
        },
        "Delay": {
          "type": "dword",
          "value": 4294967295
        },
        "EntriesList": {
          "type": "list",
          "value": [
            {
              "__struct_id": 0,
              "Active": {
                "type": "resref",
                "value": ""
              },
              "Index": {
                "type": "dword",
                "value": 2
              },
              "IsChild": {
                "type": "byte",
                "value": 1
              },
              "LinkComment": {
                "type": "cexostring",
                "value": ""
              }
            }
          ]
        },
        "Quest": {
          "type": "cexostring",
          "value": ""
        },
        "Script": {
          "type": "resref",
          "value": ""
        },
        "Sound": {
          "type": "resref",
          "value": ""
        },
        "Text": {
          "type": "cexolocstring",
          "value": {
            "id": 70927
          }
        }
      },
      {
        "__struct_id": 1,
        "Animation": {
          "type": "dword",
          "value": 0
        },
        "AnimLoop": {
          "type": "byte",
          "value": 1
        },
        "Comment": {
          "type": "cexostring",
          "value": ""
        },
        "Delay": {
          "type": "dword",
          "value": 4294967295
        },
        "EntriesList": {
          "type": "list",
          "value": [
            {
              "__struct_id": 0,
              "Active": {
                "type": "resref",
                "value": ""
              },
              "Index": {
                "type": "dword",
                "value": 2
              },
              "IsChild": {
                "type": "byte",
                "value": 1
              },
              "LinkComment": {
                "type": "cexostring",
                "value": ""
              }
            }
          ]
        },
        "Quest": {
          "type": "cexostring",
          "value": ""
        },
        "Script": {
          "type": "resref",
          "value": ""
        },
        "Sound": {
          "type": "resref",
          "value": ""
        },
        "Text": {
          "type": "cexolocstring",
          "value": {
            "id": 70928
          }
        }
      },
      {
        "__struct_id": 2,
        "Animation": {
          "type": "dword",
          "value": 0
        },
        "AnimLoop": {
          "type": "byte",
          "value": 1
        },
        "Comment": {
          "type": "cexostring",
          "value": ""
        },
        "Delay": {
          "type": "dword",
          "value": 4294967295
        },
        "EntriesList": {
          "type": "list",
          "value": [
            {
              "__struct_id": 0,
              "Active": {
                "type": "resref",
                "value": ""
              },
              "Index": {
                "type": "dword",
                "value": 2
              },
              "IsChild": {
                "type": "byte",
                "value": 0
              }
            }
          ]
        },
        "Quest": {
          "type": "cexostring",
          "value": ""
        },
        "Script": {
          "type": "resref",
          "value": ""
        },
        "Sound": {
          "type": "resref",
          "value": ""
        },
        "Text": {
          "type": "cexolocstring",
          "value": {
            "id": 70929
          }
        }
      },
      {
        "__struct_id": 3,
        "Animation": {
          "type": "dword",
          "value": 0
        },
        "AnimLoop": {
          "type": "byte",
          "value": 1
        },
        "Comment": {
          "type": "cexostring",
          "value": ""
        },
        "Delay": {
          "type": "dword",
          "value": 4294967295
        },
        "EntriesList": {
          "type": "list",
          "value": [
            {
              "__struct_id": 0,
              "Active": {
                "type": "resref",
                "value": "con_hblake_1"
              },
              "Index": {
                "type": "dword",
                "value": 19
              },
              "IsChild": {
                "type": "byte",
                "value": 0
              }
            },
            {
              "__struct_id": 1,
              "Active": {
                "type": "resref",
                "value": ""
              },
              "Index": {
                "type": "dword",
                "value": 13
              },
              "IsChild": {
                "type": "byte",
                "value": 0
              }
            },
            {
              "__struct_id": 2,
              "Active": {
                "type": "resref",
                "value": ""
              },
              "Index": {
                "type": "dword",
                "value": 3
              },
              "IsChild": {
                "type": "byte",
                "value": 0
              }
            }
          ]
        },
        "Quest": {
          "type": "cexostring",
          "value": ""
        },
        "Script": {
          "type": "resref",
          "value": ""
        },
        "Sound": {
          "type": "resref",
          "value": ""
        },
        "Text": {
          "type": "cexolocstring",
          "value": {}
        }
      },
      {
        "__struct_id": 4,
        "Animation": {
          "type": "dword",
          "value": 0
        },
        "AnimLoop": {
          "type": "byte",
          "value": 1
        },
        "Comment": {
          "type": "cexostring",
          "value": ""
        },
        "Delay": {
          "type": "dword",
          "value": 4294967295
        },
        "EntriesList": {
          "type": "list",
          "value": [
            {
              "__struct_id": 0,
              "Active": {
                "type": "resref",
                "value": ""
              },
              "Index": {
                "type": "dword",
                "value": 4
              },
              "IsChild": {
                "type": "byte",
                "value": 0
              }
            }
          ]
        },
        "Quest": {
          "type": "cexostring",
          "value": ""
        },
        "Script": {
          "type": "resref",
          "value": ""
        },
        "Sound": {
          "type": "resref",
          "value": ""
        },
        "Text": {
          "type": "cexolocstring",
          "value": {
            "id": 70930
          }
        }
      },
      {
        "__struct_id": 5,
        "Animation": {
          "type": "dword",
          "value": 0
        },
        "AnimLoop": {
          "type": "byte",
          "value": 1
        },
        "Comment": {
          "type": "cexostring",
          "value": ""
        },
        "Delay": {
          "type": "dword",
          "value": 4294967295
        },
        "EntriesList": {
          "type": "list",
          "value": [
            {
              "__struct_id": 0,
              "Active": {
                "type": "resref",
                "value": ""
              },
              "Index": {
                "type": "dword",
                "value": 5
              },
              "IsChild": {
                "type": "byte",
                "value": 0
              }
            }
          ]
        },
        "Quest": {
          "type": "cexostring",
          "value": ""
        },
        "Script": {
          "type": "resref",
          "value": "act_q1hkobold_11"
        },
        "Sound": {
          "type": "resref",
          "value": ""
        },
        "Text": {
          "type": "cexolocstring",
          "value": {
            "id": 70931
          }
        }
      },
      {
        "__struct_id": 6,
        "Animation": {
          "type": "dword",
          "value": 0
        },
        "AnimLoop": {
          "type": "byte",
          "value": 1
        },
        "Comment": {
          "type": "cexostring",
          "value": ""
        },
        "Delay": {
          "type": "dword",
          "value": 4294967295
        },
        "EntriesList": {
          "type": "list",
          "value": []
        },
        "Quest": {
          "type": "cexostring",
          "value": ""
        },
        "Script": {
          "type": "resref",
          "value": "act_q1hkobold_9"
        },
        "Sound": {
          "type": "resref",
          "value": ""
        },
        "Text": {
          "type": "cexolocstring",
          "value": {}
        }
      },
      {
        "__struct_id": 7,
        "Animation": {
          "type": "dword",
          "value": 0
        },
        "AnimLoop": {
          "type": "byte",
          "value": 1
        },
        "Comment": {
          "type": "cexostring",
          "value": ""
        },
        "Delay": {
          "type": "dword",
          "value": 4294967295
        },
        "EntriesList": {
          "type": "list",
          "value": [
            {
              "__struct_id": 0,
              "Active": {
                "type": "resref",
                "value": ""
              },
              "Index": {
                "type": "dword",
                "value": 6
              },
              "IsChild": {
                "type": "byte",
                "value": 0
              }
            }
          ]
        },
        "Quest": {
          "type": "cexostring",
          "value": ""
        },
        "Script": {
          "type": "resref",
          "value": "act_q1hkobold_12"
        },
        "Sound": {
          "type": "resref",
          "value": ""
        },
        "Text": {
          "type": "cexolocstring",
          "value": {
            "id": 70932
          }
        }
      },
      {
        "__struct_id": 8,
        "Animation": {
          "type": "dword",
          "value": 0
        },
        "AnimLoop": {
          "type": "byte",
          "value": 1
        },
        "Comment": {
          "type": "cexostring",
          "value": ""
        },
        "Delay": {
          "type": "dword",
          "value": 4294967295
        },
        "EntriesList": {
          "type": "list",
          "value": [
            {
              "__struct_id": 0,
              "Active": {
                "type": "resref",
                "value": ""
              },
              "Index": {
                "type": "dword",
                "value": 7
              },
              "IsChild": {
                "type": "byte",
                "value": 0
              }
            }
          ]
        },
        "Quest": {
          "type": "cexostring",
          "value": ""
        },
        "Script": {
          "type": "resref",
          "value": ""
        },
        "Sound": {
          "type": "resref",
          "value": ""
        },
        "Text": {
          "type": "cexolocstring",
          "value": {
            "id": 70933
          }
        }
      },
      {
        "__struct_id": 9,
        "Animation": {
          "type": "dword",
          "value": 0
        },
        "AnimLoop": {
          "type": "byte",
          "value": 1
        },
        "Comment": {
          "type": "cexostring",
          "value": ""
        },
        "Delay": {
          "type": "dword",
          "value": 4294967295
        },
        "EntriesList": {
          "type": "list",
          "value": []
        },
        "Quest": {
          "type": "cexostring",
          "value": ""
        },
        "Script": {
          "type": "resref",
          "value": "act_q1hkobold_7"
        },
        "Sound": {
          "type": "resref",
          "value": ""
        },
        "Text": {
          "type": "cexolocstring",
          "value": {}
        }
      },
      {
        "__struct_id": 10,
        "Animation": {
          "type": "dword",
          "value": 0
        },
        "AnimLoop": {
          "type": "byte",
          "value": 1
        },
        "Comment": {
          "type": "cexostring",
          "value": ""
        },
        "Delay": {
          "type": "dword",
          "value": 4294967295
        },
        "EntriesList": {
          "type": "list",
          "value": [
            {
              "__struct_id": 0,
              "Active": {
                "type": "resref",
                "value": ""
              },
              "Index": {
                "type": "dword",
                "value": 8
              },
              "IsChild": {
                "type": "byte",
                "value": 0
              }
            }
          ]
        },
        "Quest": {
          "type": "cexostring",
          "value": ""
        },
        "Script": {
          "type": "resref",
          "value": ""
        },
        "Sound": {
          "type": "resref",
          "value": ""
        },
        "Text": {
          "type": "cexolocstring",
          "value": {
            "id": 70934
          }
        }
      },
      {
        "__struct_id": 11,
        "Animation": {
          "type": "dword",
          "value": 0
        },
        "AnimLoop": {
          "type": "byte",
          "value": 1
        },
        "Comment": {
          "type": "cexostring",
          "value": ""
        },
        "Delay": {
          "type": "dword",
          "value": 4294967295
        },
        "EntriesList": {
          "type": "list",
          "value": [
            {
              "__struct_id": 0,
              "Active": {
                "type": "resref",
                "value": ""
              },
              "Index": {
                "type": "dword",
                "value": 14
              },
              "IsChild": {
                "type": "byte",
                "value": 1
              },
              "LinkComment": {
                "type": "cexostring",
                "value": ""
              }
            }
          ]
        },
        "Quest": {
          "type": "cexostring",
          "value": "q1bfamily"
        },
        "QuestEntry": {
          "type": "dword",
          "value": 30
        },
        "Script": {
          "type": "resref",
          "value": ""
        },
        "Sound": {
          "type": "resref",
          "value": ""
        },
        "Text": {
          "type": "cexolocstring",
          "value": {
            "id": 70935
          }
        }
      },
      {
        "__struct_id": 12,
        "Animation": {
          "type": "dword",
          "value": 0
        },
        "AnimLoop": {
          "type": "byte",
          "value": 1
        },
        "Comment": {
          "type": "cexostring",
          "value": ""
        },
        "Delay": {
          "type": "dword",
          "value": 4294967295
        },
        "EntriesList": {
          "type": "list",
          "value": [
            {
              "__struct_id": 0,
              "Active": {
                "type": "resref",
                "value": "con_q1hkobold_2"
              },
              "Index": {
                "type": "dword",
                "value": 10
              },
              "IsChild": {
                "type": "byte",
                "value": 0
              }
            },
            {
              "__struct_id": 1,
              "Active": {
                "type": "resref",
                "value": ""
              },
              "Index": {
                "type": "dword",
                "value": 9
              },
              "IsChild": {
                "type": "byte",
                "value": 0
              }
            }
          ]
        },
        "Quest": {
          "type": "cexostring",
          "value": ""
        },
        "Script": {
          "type": "resref",
          "value": "act_q1hkobold_4"
        },
        "Sound": {
          "type": "resref",
          "value": ""
        },
        "Text": {
          "type": "cexolocstring",
          "value": {
            "id": 70936
          }
        }
      },
      {
        "__struct_id": 13,
        "Animation": {
          "type": "dword",
          "value": 0
        },
        "AnimLoop": {
          "type": "byte",
          "value": 1
        },
        "Comment": {
          "type": "cexostring",
          "value": ""
        },
        "Delay": {
          "type": "dword",
          "value": 4294967295
        },
        "EntriesList": {
          "type": "list",
          "value": [
            {
              "__struct_id": 0,
              "Active": {
                "type": "resref",
                "value": ""
              },
              "Index": {
                "type": "dword",
                "value": 14
              },
              "IsChild": {
                "type": "byte",
                "value": 1
              },
              "LinkComment": {
                "type": "cexostring",
                "value": ""
              }
            }
          ]
        },
        "Quest": {
          "type": "cexostring",
          "value": ""
        },
        "Script": {
          "type": "resref",
          "value": ""
        },
        "Sound": {
          "type": "resref",
          "value": ""
        },
        "Text": {
          "type": "cexolocstring",
          "value": {
            "id": 70937
          }
        }
      },
      {
        "__struct_id": 14,
        "Animation": {
          "type": "dword",
          "value": 0
        },
        "AnimLoop": {
          "type": "byte",
          "value": 1
        },
        "Comment": {
          "type": "cexostring",
          "value": ""
        },
        "Delay": {
          "type": "dword",
          "value": 4294967295
        },
        "EntriesList": {
          "type": "list",
          "value": [
            {
              "__struct_id": 0,
              "Active": {
                "type": "resref",
                "value": ""
              },
              "Index": {
                "type": "dword",
                "value": 2
              },
              "IsChild": {
                "type": "byte",
                "value": 1
              },
              "LinkComment": {
                "type": "cexostring",
                "value": ""
              }
            }
          ]
        },
        "Quest": {
          "type": "cexostring",
          "value": ""
        },
        "Script": {
          "type": "resref",
          "value": ""
        },
        "Sound": {
          "type": "resref",
          "value": ""
        },
        "Text": {
          "type": "cexolocstring",
          "value": {
            "id": 70938
          }
        }
      },
      {
        "__struct_id": 15,
        "Animation": {
          "type": "dword",
          "value": 0
        },
        "AnimLoop": {
          "type": "byte",
          "value": 1
        },
        "Comment": {
          "type": "cexostring",
          "value": ""
        },
        "Delay": {
          "type": "dword",
          "value": 4294967295
        },
        "EntriesList": {
          "type": "list",
          "value": [
            {
              "__struct_id": 0,
              "Active": {
                "type": "resref",
                "value": ""
              },
              "Index": {
                "type": "dword",
                "value": 2
              },
              "IsChild": {
                "type": "byte",
                "value": 1
              },
              "LinkComment": {
                "type": "cexostring",
                "value": ""
              }
            }
          ]
        },
        "Quest": {
          "type": "cexostring",
          "value": ""
        },
        "Script": {
          "type": "resref",
          "value": ""
        },
        "Sound": {
          "type": "resref",
          "value": ""
        },
        "Text": {
          "type": "cexolocstring",
          "value": {
            "id": 70939
          }
        }
      },
      {
        "__struct_id": 16,
        "Animation": {
          "type": "dword",
          "value": 0
        },
        "AnimLoop": {
          "type": "byte",
          "value": 1
        },
        "Comment": {
          "type": "cexostring",
          "value": ""
        },
        "Delay": {
          "type": "dword",
          "value": 4294967295
        },
        "EntriesList": {
          "type": "list",
          "value": []
        },
        "Quest": {
          "type": "cexostring",
          "value": ""
        },
        "Script": {
          "type": "resref",
          "value": ""
        },
        "Sound": {
          "type": "resref",
          "value": ""
        },
        "Text": {
          "type": "cexolocstring",
          "value": {}
        }
      },
      {
        "__struct_id": 17,
        "Animation": {
          "type": "dword",
          "value": 0
        },
        "AnimLoop": {
          "type": "byte",
          "value": 1
        },
        "Comment": {
          "type": "cexostring",
          "value": ""
        },
        "Delay": {
          "type": "dword",
          "value": 4294967295
        },
        "EntriesList": {
          "type": "list",
          "value": [
            {
              "__struct_id": 0,
              "Active": {
                "type": "resref",
                "value": ""
              },
              "Index": {
                "type": "dword",
                "value": 11
              },
              "IsChild": {
                "type": "byte",
                "value": 0
              }
            }
          ]
        },
        "Quest": {
          "type": "cexostring",
          "value": ""
        },
        "Script": {
          "type": "resref",
          "value": "q1h_endcon_kob"
        },
        "Sound": {
          "type": "resref",
          "value": ""
        },
        "Text": {
          "type": "cexolocstring",
          "value": {
            "id": 70940
          }
        }
      },
      {
        "__struct_id": 18,
        "Animation": {
          "type": "dword",
          "value": 0
        },
        "AnimLoop": {
          "type": "byte",
          "value": 1
        },
        "Comment": {
          "type": "cexostring",
          "value": ""
        },
        "Delay": {
          "type": "dword",
          "value": 4294967295
        },
        "EntriesList": {
          "type": "list",
          "value": []
        },
        "Quest": {
          "type": "cexostring",
          "value": ""
        },
        "Script": {
          "type": "resref",
          "value": ""
        },
        "Sound": {
          "type": "resref",
          "value": ""
        },
        "Text": {
          "type": "cexolocstring",
          "value": {}
        }
      },
      {
        "__struct_id": 19,
        "Animation": {
          "type": "dword",
          "value": 0
        },
        "AnimLoop": {
          "type": "byte",
          "value": 1
        },
        "Comment": {
          "type": "cexostring",
          "value": ""
        },
        "Delay": {
          "type": "dword",
          "value": 4294967295
        },
        "EntriesList": {
          "type": "list",
          "value": [
            {
              "__struct_id": 0,
              "Active": {
                "type": "resref",
                "value": ""
              },
              "Index": {
                "type": "dword",
                "value": 12
              },
              "IsChild": {
                "type": "byte",
                "value": 0
              }
            }
          ]
        },
        "Quest": {
          "type": "cexostring",
          "value": ""
        },
        "Script": {
          "type": "resref",
          "value": "act_q1h1kobold_1"
        },
        "Sound": {
          "type": "resref",
          "value": ""
        },
        "Text": {
          "type": "cexolocstring",
          "value": {
            "id": 70941
          }
        }
      },
      {
        "__struct_id": 20,
        "Animation": {
          "type": "dword",
          "value": 0
        },
        "AnimLoop": {
          "type": "byte",
          "value": 1
        },
        "Comment": {
          "type": "cexostring",
          "value": ""
        },
        "Delay": {
          "type": "dword",
          "value": 4294967295
        },
        "EntriesList": {
          "type": "list",
          "value": []
        },
        "Quest": {
          "type": "cexostring",
          "value": ""
        },
        "Script": {
          "type": "resref",
          "value": ""
        },
        "Sound": {
          "type": "resref",
          "value": ""
        },
        "Text": {
          "type": "cexolocstring",
          "value": {}
        }
      },
      {
        "__struct_id": 21,
        "Animation": {
          "type": "dword",
          "value": 0
        },
        "AnimLoop": {
          "type": "byte",
          "value": 1
        },
        "Comment": {
          "type": "cexostring",
          "value": ""
        },
        "Delay": {
          "type": "dword",
          "value": 4294967295
        },
        "EntriesList": {
          "type": "list",
          "value": [
            {
              "__struct_id": 0,
              "Active": {
                "type": "resref",
                "value": ""
              },
              "Index": {
                "type": "dword",
                "value": 14
              },
              "IsChild": {
                "type": "byte",
                "value": 0
              }
            }
          ]
        },
        "Quest": {
          "type": "cexostring",
          "value": ""
        },
        "Script": {
          "type": "resref",
          "value": ""
        },
        "Sound": {
          "type": "resref",
          "value": ""
        },
        "Text": {
          "type": "cexolocstring",
          "value": {
            "id": 70942
          }
        }
      },
      {
        "__struct_id": 22,
        "Animation": {
          "type": "dword",
          "value": 0
        },
        "AnimLoop": {
          "type": "byte",
          "value": 1
        },
        "Comment": {
          "type": "cexostring",
          "value": ""
        },
        "Delay": {
          "type": "dword",
          "value": 4294967295
        },
        "EntriesList": {
          "type": "list",
          "value": []
        },
        "Quest": {
          "type": "cexostring",
          "value": ""
        },
        "Script": {
          "type": "resref",
          "value": ""
        },
        "Sound": {
          "type": "resref",
          "value": ""
        },
        "Text": {
          "type": "cexolocstring",
          "value": {}
        }
      },
      {
        "__struct_id": 23,
        "Animation": {
          "type": "dword",
          "value": 0
        },
        "AnimLoop": {
          "type": "byte",
          "value": 1
        },
        "Comment": {
          "type": "cexostring",
          "value": ""
        },
        "Delay": {
          "type": "dword",
          "value": 4294967295
        },
        "EntriesList": {
          "type": "list",
          "value": [
            {
              "__struct_id": 0,
              "Active": {
                "type": "resref",
                "value": "con_q1hkobold_2"
              },
              "Index": {
                "type": "dword",
                "value": 10
              },
              "IsChild": {
                "type": "byte",
                "value": 1
              },
              "LinkComment": {
                "type": "cexostring",
                "value": ""
              }
            },
            {
              "__struct_id": 1,
              "Active": {
                "type": "resref",
                "value": ""
              },
              "Index": {
                "type": "dword",
                "value": 9
              },
              "IsChild": {
                "type": "byte",
                "value": 1
              },
              "LinkComment": {
                "type": "cexostring",
                "value": ""
              }
            }
          ]
        },
        "Quest": {
          "type": "cexostring",
          "value": ""
        },
        "Script": {
          "type": "resref",
          "value": ""
        },
        "Sound": {
          "type": "resref",
          "value": ""
        },
        "Text": {
          "type": "cexolocstring",
          "value": {
            "id": 70943
          }
        }
      },
      {
        "__struct_id": 24,
        "Animation": {
          "type": "dword",
          "value": 0
        },
        "AnimLoop": {
          "type": "byte",
          "value": 1
        },
        "Comment": {
          "type": "cexostring",
          "value": ""
        },
        "Delay": {
          "type": "dword",
          "value": 4294967295
        },
        "EntriesList": {
          "type": "list",
          "value": [
            {
              "__struct_id": 0,
              "Active": {
                "type": "resref",
                "value": ""
              },
              "Index": {
                "type": "dword",
                "value": 16
              },
              "IsChild": {
                "type": "byte",
                "value": 0
              }
            },
            {
              "__struct_id": 1,
              "Active": {
                "type": "resref",
                "value": ""
              },
              "Index": {
                "type": "dword",
                "value": 15
              },
              "IsChild": {
                "type": "byte",
                "value": 0
              }
            }
          ]
        },
        "Quest": {
          "type": "cexostring",
          "value": ""
        },
        "Script": {
          "type": "resref",
          "value": ""
        },
        "Sound": {
          "type": "resref",
          "value": ""
        },
        "Text": {
          "type": "cexolocstring",
          "value": {
            "id": 70944
          }
        }
      },
      {
        "__struct_id": 25,
        "Animation": {
          "type": "dword",
          "value": 0
        },
        "AnimLoop": {
          "type": "byte",
          "value": 1
        },
        "Comment": {
          "type": "cexostring",
          "value": ""
        },
        "Delay": {
          "type": "dword",
          "value": 4294967295
        },
        "EntriesList": {
          "type": "list",
          "value": [
            {
              "__struct_id": 0,
              "Active": {
                "type": "resref",
                "value": ""
              },
              "Index": {
                "type": "dword",
                "value": 12
              },
              "IsChild": {
                "type": "byte",
                "value": 1
              },
              "LinkComment": {
                "type": "cexostring",
                "value": ""
              }
            }
          ]
        },
        "Quest": {
          "type": "cexostring",
          "value": ""
        },
        "Script": {
          "type": "resref",
          "value": ""
        },
        "Sound": {
          "type": "resref",
          "value": ""
        },
        "Text": {
          "type": "cexolocstring",
          "value": {
            "id": 70945
          }
        }
      },
      {
        "__struct_id": 26,
        "Animation": {
          "type": "dword",
          "value": 0
        },
        "AnimLoop": {
          "type": "byte",
          "value": 1
        },
        "Comment": {
          "type": "cexostring",
          "value": ""
        },
        "Delay": {
          "type": "dword",
          "value": 4294967295
        },
        "EntriesList": {
          "type": "list",
          "value": [
            {
              "__struct_id": 0,
              "Active": {
                "type": "resref",
                "value": ""
              },
              "Index": {
                "type": "dword",
                "value": 17
              },
              "IsChild": {
                "type": "byte",
                "value": 0
              }
            }
          ]
        },
        "Quest": {
          "type": "cexostring",
          "value": ""
        },
        "Script": {
          "type": "resref",
          "value": ""
        },
        "Sound": {
          "type": "resref",
          "value": ""
        },
        "Text": {
          "type": "cexolocstring",
          "value": {}
        }
      },
      {
        "__struct_id": 27,
        "Animation": {
          "type": "dword",
          "value": 0
        },
        "AnimLoop": {
          "type": "byte",
          "value": 1
        },
        "Comment": {
          "type": "cexostring",
          "value": ""
        },
        "Delay": {
          "type": "dword",
          "value": 4294967295
        },
        "EntriesList": {
          "type": "list",
          "value": [
            {
              "__struct_id": 0,
              "Active": {
                "type": "resref",
                "value": ""
              },
              "Index": {
                "type": "dword",
                "value": 18
              },
              "IsChild": {
                "type": "byte",
                "value": 0
              }
            }
          ]
        },
        "Quest": {
          "type": "cexostring",
          "value": ""
        },
        "Script": {
          "type": "resref",
          "value": ""
        },
        "Sound": {
          "type": "resref",
          "value": ""
        },
        "Text": {
          "type": "cexolocstring",
          "value": {
            "id": 70946
          }
        }
      },
      {
        "__struct_id": 28,
        "Animation": {
          "type": "dword",
          "value": 0
        },
        "AnimLoop": {
          "type": "byte",
          "value": 1
        },
        "Comment": {
          "type": "cexostring",
          "value": ""
        },
        "Delay": {
          "type": "dword",
          "value": 4294967295
        },
        "EntriesList": {
          "type": "list",
          "value": [
            {
              "__struct_id": 0,
              "Active": {
                "type": "resref",
                "value": ""
              },
              "Index": {
                "type": "dword",
                "value": 12
              },
              "IsChild": {
                "type": "byte",
                "value": 1
              },
              "LinkComment": {
                "type": "cexostring",
                "value": ""
              }
            }
          ]
        },
        "Quest": {
          "type": "cexostring",
          "value": ""
        },
        "Script": {
          "type": "resref",
          "value": ""
        },
        "Sound": {
          "type": "resref",
          "value": ""
        },
        "Text": {
          "type": "cexolocstring",
          "value": {
            "id": 70947
          }
        }
      },
      {
        "__struct_id": 29,
        "Animation": {
          "type": "dword",
          "value": 0
        },
        "AnimLoop": {
          "type": "byte",
          "value": 1
        },
        "Comment": {
          "type": "cexostring",
          "value": ""
        },
        "Delay": {
          "type": "dword",
          "value": 4294967295
        },
        "EntriesList": {
          "type": "list",
          "value": [
            {
              "__struct_id": 0,
              "Active": {
                "type": "resref",
                "value": ""
              },
              "Index": {
                "type": "dword",
                "value": 20
              },
              "IsChild": {
                "type": "byte",
                "value": 0
              }
            }
          ]
        },
        "Quest": {
          "type": "cexostring",
          "value": ""
        },
        "Script": {
          "type": "resref",
          "value": ""
        },
        "Sound": {
          "type": "resref",
          "value": ""
        },
        "Text": {
          "type": "cexolocstring",
          "value": {}
        }
      },
      {
        "__struct_id": 30,
        "Animation": {
          "type": "dword",
          "value": 0
        },
        "AnimLoop": {
          "type": "byte",
          "value": 1
        },
        "Comment": {
          "type": "cexostring",
          "value": ""
        },
        "Delay": {
          "type": "dword",
          "value": 4294967295
        },
        "EntriesList": {
          "type": "list",
          "value": [
            {
              "__struct_id": 0,
              "Active": {
                "type": "resref",
                "value": ""
              },
              "Index": {
                "type": "dword",
                "value": 21
              },
              "IsChild": {
                "type": "byte",
                "value": 0
              }
            }
          ]
        },
        "Quest": {
          "type": "cexostring",
          "value": ""
        },
        "Script": {
          "type": "resref",
          "value": ""
        },
        "Sound": {
          "type": "resref",
          "value": ""
        },
        "Text": {
          "type": "cexolocstring",
          "value": {}
        }
      },
      {
        "__struct_id": 31,
        "Animation": {
          "type": "dword",
          "value": 0
        },
        "AnimLoop": {
          "type": "byte",
          "value": 1
        },
        "Comment": {
          "type": "cexostring",
          "value": ""
        },
        "Delay": {
          "type": "dword",
          "value": 4294967295
        },
        "EntriesList": {
          "type": "list",
          "value": [
            {
              "__struct_id": 0,
              "Active": {
                "type": "resref",
                "value": ""
              },
              "Index": {
                "type": "dword",
                "value": 12
              },
              "IsChild": {
                "type": "byte",
                "value": 1
              },
              "LinkComment": {
                "type": "cexostring",
                "value": ""
              }
            }
          ]
        },
        "Quest": {
          "type": "cexostring",
          "value": ""
        },
        "Script": {
          "type": "resref",
          "value": ""
        },
        "Sound": {
          "type": "resref",
          "value": ""
        },
        "Text": {
          "type": "cexolocstring",
          "value": {}
        }
      },
      {
        "__struct_id": 32,
        "Animation": {
          "type": "dword",
          "value": 0
        },
        "AnimLoop": {
          "type": "byte",
          "value": 1
        },
        "Comment": {
          "type": "cexostring",
          "value": ""
        },
        "Delay": {
          "type": "dword",
          "value": 4294967295
        },
        "EntriesList": {
          "type": "list",
          "value": []
        },
        "Quest": {
          "type": "cexostring",
          "value": ""
        },
        "Script": {
          "type": "resref",
          "value": ""
        },
        "Sound": {
          "type": "resref",
          "value": ""
        },
        "Text": {
          "type": "cexolocstring",
          "value": {}
        }
      }
    ]
  },
  "StartingList": {
    "type": "list",
    "value": [
      {
        "__struct_id": 0,
        "Active": {
          "type": "resref",
          "value": "con_q1hblake_3"
        },
        "Index": {
          "type": "dword",
          "value": 22
        }
      },
      {
        "__struct_id": 1,
        "Active": {
          "type": "resref",
          "value": "con_q1hkobold_3"
        },
        "Index": {
          "type": "dword",
          "value": 1
        }
      },
      {
        "__struct_id": 2,
        "Active": {
          "type": "resref",
          "value": ""
        },
        "Index": {
          "type": "dword",
          "value": 0
        }
      }
    ]
  }
}
