{
  "__data_type": "UTW ",
  "Comment": {
    "type": "cexostring",
    "value": ""
  },
  "Description": {
    "type": "cexolocstring",
    "value": {}
  },
  "HasMapNote": {
    "type": "byte",
    "value": 0
  },
  "LinkedTo": {
    "type": "cexostring",
    "value": ""
  },
  "LocalizedName": {
    "type": "cexolocstring",
    "value": {
      "id": 49179
    }
  },
  "PaletteID": {
    "type": "byte",
    "value": 5
  },
  "Tag": {
    "type": "cexostring",
    "value": "M4QD07_ENTER"
  },
  "TemplateResRef": {
    "type": "resref",
    "value": "m4qd07_enter"
  }
}
