{
  "__data_type": "UTW ",
  "Appearance": {
    "type": "byte",
    "value": 1
  },
  "Comment": {
    "type": "cexostring",
    "value": "Soldiers from A04 move here to A12 (near gates and then disappear)"
  },
  "Description": {
    "type": "cexolocstring",
    "value": {}
  },
  "HasMapNote": {
    "type": "byte",
    "value": 0
  },
  "LinkedTo": {
    "type": "cexostring",
    "value": ""
  },
  "LocalizedName": {
    "type": "cexolocstring",
    "value": {
      "id": 61360
    }
  },
  "PaletteID": {
    "type": "byte",
    "value": 5
  },
  "Tag": {
    "type": "cexostring",
    "value": "WP_M4Q01BWOUN"
  },
  "TemplateResRef": {
    "type": "resref",
    "value": "wp_m4q01bwoun_01"
  }
}
